Workbook

Sheet INDICE
B2: INDICE DE INFORMACION DE LA INDUSTRIA
B3: (Hacer click sobre el titulo de interes)
A5: 1 | B5: ='Inventario Empresas Linea 1'!C2 -> EMPRESAS CON INVENTARIO CLIMATIZACIO
A6: 2 | B6: ='Inventario Empresas Linea 2'!C2 -> EMPRESAS CON INVENTARIO ELECTRODOMES
A7: 3 | B7: ='Manufactura Linea 1'!C4 -> COSTO PROMEDIO DE MANUFACTURA PARA CLIMATIZACIO CONSIDERANDO TODA LA INDUSTRIA
A8: 4 | B8: ='Manufactura Linea 2'!C4 -> COSTO PROMEDIO DE MANUFACTURA PARA ELECTRODOMES CONSIDERANDO TODA LA INDUSTRIA
A9: 5 | B9: =CONCATENATE('Informacion Linea 1'!C1," ",'Informacion Linea 1'!D1) -> INFORMACION DETALLADA PARA CLIMATIZACIO
A10: 6 | B10: =CONCATENATE('Informacion Linea 1'!C58," ",'Informacion Linea 1'!D1) -> GASTOS HISTORICOS PROMEDIO CONSIDERANDO CLIMATIZACIO
A11: 7 | B11: =CONCATENATE('Informacion Linea 2'!C1," ",'Informacion Linea 2'!D1) -> INFORMACION DETALLADA PARA ELECTRODOMES
A12: 8 | B12: =CONCATENATE('Informacion Linea 2'!C58," ",'Informacion Linea 2'!D1) -> GASTOS HISTORICOS PROMEDIO CONSIDERANDO ELECTRODOMES
A13: 9 | B13: ='Rentabilidad Linea 1'!C3 -> RENTABILIDAD POR ARTICULO DE CLIMATIZACIO
A14: 10 | B14: ='Rentabilidad Linea 2'!C3 -> RENTABILIDAD POR ARTICULO DE ELECTRODOMES
A15: 11 | B15: ='Precios Promedios'!C3 -> PRECIOS DE EXPEDITAJE (NO SE RECOMIENDA USAR ESTOS COMO REFERENCIA PARA DETERMINAR PRECIOS
A16: 12 | B16: ='Precios Promedios'!C15 -> PRECIOS DE COMPRAS DE SALDOS
A17: 13 | B17: ='Vta Industria Linea 1'!C3 -> PRECIO PROMEDIO TRANSADO ENTRE EMPRESAS POR ARTICULO Y CANTIDAD PARA EL PERIODO 7 SEGUN EL TRANSPORTE. PARA CLIMATIZACIO
A18: 14 | B18: ='Vta Industria Linea 2'!C3 -> PRECIO PROMEDIO TRANSADO ENTRE EMPRESAS POR ARTICULO Y CANTIDAD PARA EL PERIODO 7 SEGUN EL TRANSPORTE. PARA ELECTRODOMES
A19: 15 | B19: ='Actividad Empresas'!C3 -> EMPRESAS CON ACTIVIDAD
A20: 16 | B20: ='Fabricas sin Uso'!C2 -> FABRICAS QUE NO HAN SIDO UTILIZADAS EL ULTIMO PERIODO

Sheet Inventario Empresas Linea 1
C2: =UPPER(DATALOG!B651) -> EMPRESAS CON INVENTARIO CLIMATIZACIO
C3: =IF(DATALOG!C651="","",DATALOG!C651) -> Alemania | D3: =IF(DATALOG!D651="","",DATALOG!D651) -> Alemania | E3: =IF(DATALOG!E651="","",DATALOG!E651) -> Australia | F3: =IF(DATALOG!F651="","",DATALOG!F651) -> Australia | G3: =IF(DATALOG!G651="","",DATALOG!G651) -> Espana | H3: =IF(DATALOG!H651="","",DATALOG!H651) -> Espana | I3: =IF(DATALOG!I651="","",DATALOG!I651) | J3: =IF(DATALOG!J651="","",DATALOG!J651) -> Alemania | ... BL3: =IF(DATALOG!BL651="","",DATALOG!BL651)
C4: =IF(DATALOG!C652="","",DATALOG!C652) -> EstufaGas | D4: =IF(DATALOG!D652="","",DATALOG!D652) -> Inventario | E4: =IF(DATALOG!E652="","",DATALOG!E652) -> EstufaGas | F4: =IF(DATALOG!F652="","",DATALOG!F652) -> Inventario | G4: =IF(DATALOG!G652="","",DATALOG!G652) -> EstufaGas | H4: =IF(DATALOG!H652="","",DATALOG!H652) -> Inventario | I4: =IF(DATALOG!I652="","",DATALOG!I652) | J4: =IF(DATALOG!J652="","",DATALOG!J652) -> EstufaElectr | ... BL4: =IF(DATALOG!BL652="","",DATALOG!BL652)
C5: =IF(DATALOG!C653=0,"",DATALOG!C653) -> 2 | D5: =IF(DATALOG!D653=0,"",DATALOG!D653) -> 7744 | E5: =IF(DATALOG!E653=0,"",DATALOG!E653) -> 4 | F5: =IF(DATALOG!F653=0,"",DATALOG!F653) -> 6619 | G5: =IF(DATALOG!G653=0,"",DATALOG!G653) -> 2 | H5: =IF(DATALOG!H653=0,"",DATALOG!H653) -> 9800 | I5: =IF(DATALOG!I653=0,"",DATALOG!I653) | J5: =IF(DATALOG!J653=0,"",DATALOG!J653) -> 2 | ... O5: =IF(DATALOG!O653=0,"",DATALOG!O653) -> 2000 | Q5: =IF(DATALOG!Q653=0,"",DATALOG!Q653) -> 7 | R5: =IF(DATALOG!R653=0,"",DATALOG!R653) -> 7201 | S5: =IF(DATALOG!S653=0,"",DATALOG!S653) -> 4 | T5: =IF(DATALOG!T653=0,"",DATALOG!T653) -> 4749 | U5: =IF(DATALOG!U653=0,"",DATALOG!U653) -> 4 | V5: =IF(DATALOG!V653=0,"",DATALOG!V653) -> 5052 | X5: =IF(DATALOG!X653=0,"",DATALOG!X653) -> 5 | Y5: =IF(DATALOG!Y653=0,"",DATALOG!Y653) -> 36000 | Z5: =IF(DATALOG!Z653=0,"",DATALOG!Z653) -> 4 | AA5: =IF(DATALOG!AA653=0,"",DATALOG!AA653) -> 5719 | AB5: =IF(DATALOG!AB653=0,"",DATALOG!AB653) -> 4 | AC5: =IF(DATALOG!AC653=0,"",DATALOG!AC653) -> 2517 | AE5: =IF(DATALOG!AE653=0,"",DATALOG!AE653) -> 2 | AF5: =IF(DATALOG!AF653=0,"",DATALOG!AF653) -> 6303 | AG5: =IF(DATALOG!AG653=0,"",DATALOG!AG653) -> 2 | AH5: =IF(DATALOG!AH653=0,"",DATALOG!AH653) -> 10000 | AI5: =IF(DATALOG!AI653=0,"",DATALOG!AI653) -> 2 | AJ5: =IF(DATALOG!AJ653=0,"",DATALOG!AJ653) -> 7000 | AL5: =IF(DATALOG!AL653=0,"",DATALOG!AL653) -> 2 | AM5: =IF(DATALOG!AM653=0,"",DATALOG!AM653) -> 5477 | AN5: =IF(DATALOG!AN653=0,"",DATALOG!AN653) -> 2 | AO5: =IF(DATALOG!AO653=0,"",DATALOG!AO653) -> 8333 | AP5: =IF(DATALOG!AP653=0,"",DATALOG!AP653) -> 2 | AQ5: =IF(DATALOG!AQ653=0,"",DATALOG!AQ653) -> 2000 | AS5: =IF(DATALOG!AS653=0,"",DATALOG!AS653) -> 10 | AT5: =IF(DATALOG!AT653=0,"",DATALOG!AT653) -> 1601 | AU5: =IF(DATALOG!AU653=0,"",DATALOG!AU653) -> 2 | AV5: =IF(DATALOG!AV653=0,"",DATALOG!AV653) -> 12500 | AW5: =IF(DATALOG!AW653=0,"",DATALOG!AW653) -> 2 | AX5: =IF(DATALOG!AX653=0,"",DATALOG!AX653) -> 2000 | AZ5: =IF(DATALOG!AZ653=0,"",DATALOG!AZ653) | BA5: =IF(DATALOG!BA653=0,"",DATALOG!BA653) | BB5: =IF(DATALOG!BB653=0,"",DATALOG!BB653) | BC5: =IF(DATALOG!BC653=0,"",DATALOG!BC653) | BD5: =IF(DATALOG!BD653=0,"",DATALOG!BD653) | BE5: =IF(DATALOG!BE653=0,"",DATALOG!BE653) | BG5: =IF(DATALOG!BG653=0,"",DATALOG!BG653) | BH5: =IF(DATALOG!BH653=0,"",DATALOG!BH653) | BI5: =IF(DATALOG!BI653=0,"",DATALOG!BI653) | BJ5: =IF(DATALOG!BJ653=0,"",DATALOG!BJ653) | BK5: =IF(DATALOG!BK653=0,"",DATALOG!BK653) | BL5: =IF(DATALOG!BL653=0,"",DATALOG!BL653)
C6: =IF(DATALOG!C654=0,"",DATALOG!C654) -> 8 | D6: =IF(DATALOG!D654=0,"",DATALOG!D654) -> 12387 | E6: =IF(DATALOG!E654=0,"",DATALOG!E654) -> 11 | F6: =IF(DATALOG!F654=0,"",DATALOG!F654) -> 3356 | G6: =IF(DATALOG!G654=0,"",DATALOG!G654) -> 4 | H6: =IF(DATALOG!H654=0,"",DATALOG!H654) -> 1127 | I6: =IF(DATALOG!I654=0,"",DATALOG!I654) | J6: =IF(DATALOG!J654=0,"",DATALOG!J654) -> 5 | ... O6: =IF(DATALOG!O654=0,"",DATALOG!O654) -> 4252 | Q6: =IF(DATALOG!Q654=0,"",DATALOG!Q654) -> 12 | R6: =IF(DATALOG!R654=0,"",DATALOG!R654) -> 10386 | S6: =IF(DATALOG!S654=0,"",DATALOG!S654) -> 5 | T6: =IF(DATALOG!T654=0,"",DATALOG!T654) -> 2784 | U6: =IF(DATALOG!U654=0,"",DATALOG!U654) -> 6 | V6: =IF(DATALOG!V654=0,"",DATALOG!V654) -> 4002 | X6: =IF(DATALOG!X654=0,"",DATALOG!X654) -> 12 | Y6: =IF(DATALOG!Y654=0,"",DATALOG!Y654) -> 3299 | Z6: =IF(DATALOG!Z654=0,"",DATALOG!Z654) -> 5 | AA6: =IF(DATALOG!AA654=0,"",DATALOG!AA654) -> 7700 | AB6: =IF(DATALOG!AB654=0,"",DATALOG!AB654) -> 6 | AC6: =IF(DATALOG!AC654=0,"",DATALOG!AC654) -> 4000 | AE6: =IF(DATALOG!AE654=0,"",DATALOG!AE654) -> 7 | AF6: =IF(DATALOG!AF654=0,"",DATALOG!AF654) -> 8760 | AG6: =IF(DATALOG!AG654=0,"",DATALOG!AG654) -> 4 | AH6: =IF(DATALOG!AH654=0,"",DATALOG!AH654) -> 6327 | AI6: =IF(DATALOG!AI654=0,"",DATALOG!AI654) -> 4 | AJ6: =IF(DATALOG!AJ654=0,"",DATALOG!AJ654) -> 4552 | AL6: =IF(DATALOG!AL654=0,"",DATALOG!AL654) -> 9 | AM6: =IF(DATALOG!AM654=0,"",DATALOG!AM654) -> 6140 | AN6: =IF(DATALOG!AN654=0,"",DATALOG!AN654) -> 4 | AO6: =IF(DATALOG!AO654=0,"",DATALOG!AO654) -> 2000 | AP6: =IF(DATALOG!AP654=0,"",DATALOG!AP654) -> 8 | AQ6: =IF(DATALOG!AQ654=0,"",DATALOG!AQ654) -> 5820 | AS6: =IF(DATALOG!AS654=0,"",DATALOG!AS654) -> 12 | AT6: =IF(DATALOG!AT654=0,"",DATALOG!AT654) -> 2666 | AU6: =IF(DATALOG!AU654=0,"",DATALOG!AU654) -> 4 | AV6: =IF(DATALOG!AV654=0,"",DATALOG!AV654) -> 4000 | AW6: =IF(DATALOG!AW654=0,"",DATALOG!AW654) -> 8 | AX6: =IF(DATALOG!AX654=0,"",DATALOG!AX654) -> 8500 | AZ6: =IF(DATALOG!AZ654=0,"",DATALOG!AZ654) | BA6: =IF(DATALOG!BA654=0,"",DATALOG!BA654) | BB6: =IF(DATALOG!BB654=0,"",DATALOG!BB654) | BC6: =IF(DATALOG!BC654=0,"",DATALOG!BC654) | BD6: =IF(DATALOG!BD654=0,"",DATALOG!BD654) | BE6: =IF(DATALOG!BE654=0,"",DATALOG!BE654) | BG6: =IF(DATALOG!BG654=0,"",DATALOG!BG654) | BH6: =IF(DATALOG!BH654=0,"",DATALOG!BH654) | BI6: =IF(DATALOG!BI654=0,"",DATALOG!BI654) | BJ6: =IF(DATALOG!BJ654=0,"",DATALOG!BJ654) | BK6: =IF(DATALOG!BK654=0,"",DATALOG!BK654) | BL6: =IF(DATALOG!BL654=0,"",DATALOG!BL654)
C7: =IF(DATALOG!C655=0,"",DATALOG!C655) -> 10 | D7: =IF(DATALOG!D655=0,"",DATALOG!D655) -> 5000 | E7: =IF(DATALOG!E655=0,"",DATALOG!E655) -> 12 | F7: =IF(DATALOG!F655=0,"",DATALOG!F655) -> 4000 | G7: =IF(DATALOG!G655=0,"",DATALOG!G655) -> 6 | H7: =IF(DATALOG!H655=0,"",DATALOG!H655) -> 7637 | I7: =IF(DATALOG!I655=0,"",DATALOG!I655) | J7: =IF(DATALOG!J655=0,"",DATALOG!J655) -> 7 | ... O7: =IF(DATALOG!O655=0,"",DATALOG!O655) -> 6110 | Q7: =IF(DATALOG!Q655=0,"",DATALOG!Q655) -> 13 | R7: =IF(DATALOG!R655=0,"",DATALOG!R655) -> 2990 | S7: =IF(DATALOG!S655=0,"",DATALOG!S655) -> 10 | T7: =IF(DATALOG!T655=0,"",DATALOG!T655) -> 2700 | U7: =IF(DATALOG!U655=0,"",DATALOG!U655) -> 11 | V7: =IF(DATALOG!V655=0,"",DATALOG!V655) -> 6000 | X7: =IF(DATALOG!X655=0,"",DATALOG!X655) -> 13 | Y7: =IF(DATALOG!Y655=0,"",DATALOG!Y655) -> 3000 | Z7: =IF(DATALOG!Z655=0,"",DATALOG!Z655) -> 6 | AA7: =IF(DATALOG!AA655=0,"",DATALOG!AA655) -> 12897 | AB7: =IF(DATALOG!AB655=0,"",DATALOG!AB655) -> 10 | AC7: =IF(DATALOG!AC655=0,"",DATALOG!AC655) -> 6000 | AE7: =IF(DATALOG!AE655=0,"",DATALOG!AE655) -> 8 | AF7: =IF(DATALOG!AF655=0,"",DATALOG!AF655) -> 30000 | AG7: =IF(DATALOG!AG655=0,"",DATALOG!AG655) -> 5 | AH7: =IF(DATALOG!AH655=0,"",DATALOG!AH655) -> 6000 | AI7: =IF(DATALOG!AI655=0,"",DATALOG!AI655) -> 6 | AJ7: =IF(DATALOG!AJ655=0,"",DATALOG!AJ655) -> 8450 | AL7: =IF(DATALOG!AL655=0,"",DATALOG!AL655) -> 12 | AM7: =IF(DATALOG!AM655=0,"",DATALOG!AM655) -> 2703 | AN7: =IF(DATALOG!AN655=0,"",DATALOG!AN655) -> 6 | AO7: =IF(DATALOG!AO655=0,"",DATALOG!AO655) -> 8831 | AP7: =IF(DATALOG!AP655=0,"",DATALOG!AP655) -> 11 | AQ7: =IF(DATALOG!AQ655=0,"",DATALOG!AQ655) -> 4083 | AS7: =IF(DATALOG!AS655=0,"",DATALOG!AS655) -> 13 | AT7: =IF(DATALOG!AT655=0,"",DATALOG!AT655) -> 6720 | AU7: =IF(DATALOG!AU655=0,"",DATALOG!AU655) -> 6 | AV7: =IF(DATALOG!AV655=0,"",DATALOG!AV655) -> 11266 | AW7: =IF(DATALOG!AW655=0,"",DATALOG!AW655) -> 10 | AX7: =IF(DATALOG!AX655=0,"",DATALOG!AX655) -> 3000 | AZ7: =IF(DATALOG!AZ655=0,"",DATALOG!AZ655) | BA7: =IF(DATALOG!BA655=0,"",DATALOG!BA655) | BB7: =IF(DATALOG!BB655=0,"",DATALOG!BB655) | BC7: =IF(DATALOG!BC655=0,"",DATALOG!BC655) | BD7: =IF(DATALOG!BD655=0,"",DATALOG!BD655) | BE7: =IF(DATALOG!BE655=0,"",DATALOG!BE655) | BG7: =IF(DATALOG!BG655=0,"",DATALOG!BG655) | BH7: =IF(DATALOG!BH655=0,"",DATALOG!BH655) | BI7: =IF(DATALOG!BI655=0,"",DATALOG!BI655) | BJ7: =IF(DATALOG!BJ655=0,"",DATALOG!BJ655) | BK7: =IF(DATALOG!BK655=0,"",DATALOG!BK655) | BL7: =IF(DATALOG!BL655=0,"",DATALOG!BL655)
C8: =IF(DATALOG!C656=0,"",DATALOG!C656) -> 12 | D8: =IF(DATALOG!D656=0,"",DATALOG!D656) -> 8800 | E8: =IF(DATALOG!E656=0,"",DATALOG!E656) -> 13 | F8: =IF(DATALOG!F656=0,"",DATALOG!F656) -> 6217 | G8: =IF(DATALOG!G656=0,"",DATALOG!G656) -> 9 | H8: =IF(DATALOG!H656=0,"",DATALOG!H656) -> 8437 | I8: =IF(DATALOG!I656=0,"",DATALOG!I656) | J8: =IF(DATALOG!J656=0,"",DATALOG!J656) -> 10 | ... O8: =IF(DATALOG!O656=0,"",DATALOG!O656) -> 9000 | Q8: =IF(DATALOG!Q656=0,"",DATALOG!Q656) -> 14 | R8: =IF(DATALOG!R656=0,"",DATALOG!R656) -> 10143 | S8: =IF(DATALOG!S656=0,"",DATALOG!S656) -> 11 | T8: =IF(DATALOG!T656=0,"",DATALOG!T656) -> 5321 | U8: =IF(DATALOG!U656=0,"",DATALOG!U656) -> 12 | V8: =IF(DATALOG!V656=0,"",DATALOG!V656) -> 4000 | X8: =IF(DATALOG!X656=0,"",DATALOG!X656) -> 15 | Y8: =IF(DATALOG!Y656=0,"",DATALOG!Y656) -> 2000 | Z8: =IF(DATALOG!Z656=0,"",DATALOG!Z656) -> 10 | AA8: =IF(DATALOG!AA656=0,"",DATALOG!AA656) -> 1650 | AB8: =IF(DATALOG!AB656=0,"",DATALOG!AB656) -> 11 | AC8: =IF(DATALOG!AC656=0,"",DATALOG!AC656) -> 5800 | AE8: =IF(DATALOG!AE656=0,"",DATALOG!AE656) -> 10 | AF8: =IF(DATALOG!AF656=0,"",DATALOG!AF656) -> 5926 | AG8: =IF(DATALOG!AG656=0,"",DATALOG!AG656) -> 9 | AH8: =IF(DATALOG!AH656=0,"",DATALOG!AH656) -> 9365 | AI8: =IF(DATALOG!AI656=0,"",DATALOG!AI656) -> 8 | AJ8: =IF(DATALOG!AJ656=0,"",DATALOG!AJ656) -> 11250 | AL8: =IF(DATALOG!AL656=0,"",DATALOG!AL656) -> 13 | AM8: =IF(DATALOG!AM656=0,"",DATALOG!AM656) -> 757 | AN8: =IF(DATALOG!AN656=0,"",DATALOG!AN656) -> 9 | AO8: =IF(DATALOG!AO656=0,"",DATALOG!AO656) -> 15608 | AP8: =IF(DATALOG!AP656=0,"",DATALOG!AP656) -> 16 | AQ8: =IF(DATALOG!AQ656=0,"",DATALOG!AQ656) -> 6500 | AS8: =IF(DATALOG!AS656=0,"",DATALOG!AS656) -> 15 | AT8: =IF(DATALOG!AT656=0,"",DATALOG!AT656) -> 3000 | AU8: =IF(DATALOG!AU656=0,"",DATALOG!AU656) -> 11 | AV8: =IF(DATALOG!AV656=0,"",DATALOG!AV656) -> 3790 | AW8: =IF(DATALOG!AW656=0,"",DATALOG!AW656) -> 11 | AX8: =IF(DATALOG!AX656=0,"",DATALOG!AX656) -> 4105 | AZ8: =IF(DATALOG!AZ656=0,"",DATALOG!AZ656) | BA8: =IF(DATALOG!BA656=0,"",DATALOG!BA656) | BB8: =IF(DATALOG!BB656=0,"",DATALOG!BB656) | BC8: =IF(DATALOG!BC656=0,"",DATALOG!BC656) | BD8: =IF(DATALOG!BD656=0,"",DATALOG!BD656) | BE8: =IF(DATALOG!BE656=0,"",DATALOG!BE656) | BG8: =IF(DATALOG!BG656=0,"",DATALOG!BG656) | BH8: =IF(DATALOG!BH656=0,"",DATALOG!BH656) | BI8: =IF(DATALOG!BI656=0,"",DATALOG!BI656) | BJ8: =IF(DATALOG!BJ656=0,"",DATALOG!BJ656) | BK8: =IF(DATALOG!BK656=0,"",DATALOG!BK656) | BL8: =IF(DATALOG!BL656=0,"",DATALOG!BL656)
C9: =IF(DATALOG!C657=0,"",DATALOG!C657) -> 14 | D9: =IF(DATALOG!D657=0,"",DATALOG!D657) -> 9000 | E9: =IF(DATALOG!E657=0,"",DATALOG!E657) -> 14 | F9: =IF(DATALOG!F657=0,"",DATALOG!F657) -> 4200 | G9: =IF(DATALOG!G657=0,"",DATALOG!G657) -> 10 | H9: =IF(DATALOG!H657=0,"",DATALOG!H657) -> 5100 | I9: =IF(DATALOG!I657=0,"",DATALOG!I657) | J9: =IF(DATALOG!J657=0,"",DATALOG!J657) -> 12 | ... O9: =IF(DATALOG!O657=0,"",DATALOG!O657) -> 6750 | Q9: =IF(DATALOG!Q657=0,"",DATALOG!Q657) -> 15 | R9: =IF(DATALOG!R657=0,"",DATALOG!R657) -> 3000 | S9: =IF(DATALOG!S657=0,"",DATALOG!S657) -> 12 | T9: =IF(DATALOG!T657=0,"",DATALOG!T657) -> 6752 | U9: =IF(DATALOG!U657=0,"",DATALOG!U657) -> 13 | V9: =IF(DATALOG!V657=0,"",DATALOG!V657) -> 7572 | X9: =IF(DATALOG!X657=0,"",DATALOG!X657) -> 16 | Y9: =IF(DATALOG!Y657=0,"",DATALOG!Y657) -> 6000 | Z9: =IF(DATALOG!Z657=0,"",DATALOG!Z657) -> 11 | AA9: =IF(DATALOG!AA657=0,"",DATALOG!AA657) -> 6735 | AB9: =IF(DATALOG!AB657=0,"",DATALOG!AB657) -> 12 | AC9: =IF(DATALOG!AC657=0,"",DATALOG!AC657) -> 4000 | AE9: =IF(DATALOG!AE657=0,"",DATALOG!AE657) -> 12 | AF9: =IF(DATALOG!AF657=0,"",DATALOG!AF657) -> 7493 | AG9: =IF(DATALOG!AG657=0,"",DATALOG!AG657) -> 10 | AH9: =IF(DATALOG!AH657=0,"",DATALOG!AH657) -> 1250 | AI9: =IF(DATALOG!AI657=0,"",DATALOG!AI657) -> 9 | AJ9: =IF(DATALOG!AJ657=0,"",DATALOG!AJ657) -> 11250 | AL9: =IF(DATALOG!AL657=0,"",DATALOG!AL657) -> 15 | AM9: =IF(DATALOG!AM657=0,"",DATALOG!AM657) -> 3000 | AN9: =IF(DATALOG!AN657=0,"",DATALOG!AN657) -> 11 | AO9: =IF(DATALOG!AO657=0,"",DATALOG!AO657) -> 4000 | AP9: =IF(DATALOG!AP657=0,"",DATALOG!AP657) -> 17 | AQ9: =IF(DATALOG!AQ657=0,"",DATALOG!AQ657) -> 2138 | AS9: =IF(DATALOG!AS657=0,"",DATALOG!AS657) -> 16 | AT9: =IF(DATALOG!AT657=0,"",DATALOG!AT657) -> 4709 | AU9: =IF(DATALOG!AU657=0,"",DATALOG!AU657) -> 12 | AV9: =IF(DATALOG!AV657=0,"",DATALOG!AV657) -> 5000 | AW9: =IF(DATALOG!AW657=0,"",DATALOG!AW657) -> 13 | AX9: =IF(DATALOG!AX657=0,"",DATALOG!AX657) -> 5300 | AZ9: =IF(DATALOG!AZ657=0,"",DATALOG!AZ657) | BA9: =IF(DATALOG!BA657=0,"",DATALOG!BA657) | BB9: =IF(DATALOG!BB657=0,"",DATALOG!BB657) | BC9: =IF(DATALOG!BC657=0,"",DATALOG!BC657) | BD9: =IF(DATALOG!BD657=0,"",DATALOG!BD657) | BE9: =IF(DATALOG!BE657=0,"",DATALOG!BE657) | BG9: =IF(DATALOG!BG657=0,"",DATALOG!BG657) | BH9: =IF(DATALOG!BH657=0,"",DATALOG!BH657) | BI9: =IF(DATALOG!BI657=0,"",DATALOG!BI657) | BJ9: =IF(DATALOG!BJ657=0,"",DATALOG!BJ657) | BK9: =IF(DATALOG!BK657=0,"",DATALOG!BK657) | BL9: =IF(DATALOG!BL657=0,"",DATALOG!BL657)
C10: =IF(DATALOG!C658=0,"",DATALOG!C658) -> 15 | D10: =IF(DATALOG!D658=0,"",DATALOG!D658) -> 19574 | E10: =IF(DATALOG!E658=0,"",DATALOG!E658) -> 16 | F10: =IF(DATALOG!F658=0,"",DATALOG!F658) -> 4000 | G10: =IF(DATALOG!G658=0,"",DATALOG!G658) -> 11 | H10: =IF(DATALOG!H658=0,"",DATALOG!H658) -> 4001 | I10: =IF(DATALOG!I658=0,"",DATALOG!I658) | J10: =IF(DATALOG!J658=0,"",DATALOG!J658) -> 14 | ... O10: =IF(DATALOG!O658=0,"",DATALOG!O658) -> 6280 | Q10: =IF(DATALOG!Q658=0,"",DATALOG!Q658) -> 16 | R10: =IF(DATALOG!R658=0,"",DATALOG!R658) -> 6000 | S10: =IF(DATALOG!S658=0,"",DATALOG!S658) -> 13 | T10: =IF(DATALOG!T658=0,"",DATALOG!T658) -> 984 | U10: =IF(DATALOG!U658=0,"",DATALOG!U658) -> 15 | V10: =IF(DATALOG!V658=0,"",DATALOG!V658) -> 24107 | X10: =IF(DATALOG!X658=0,"",DATALOG!X658) -> 17 | Y10: =IF(DATALOG!Y658=0,"",DATALOG!Y658) -> 18002 | Z10: =IF(DATALOG!Z658=0,"",DATALOG!Z658) -> 12 | AA10: =IF(DATALOG!AA658=0,"",DATALOG!AA658) -> 6930 | AB10: =IF(DATALOG!AB658=0,"",DATALOG!AB658) -> 13 | AC10: =IF(DATALOG!AC658=0,"",DATALOG!AC658) -> 13500 | AE10: =IF(DATALOG!AE658=0,"",DATALOG!AE658) -> 13 | AF10: =IF(DATALOG!AF658=0,"",DATALOG!AF658) -> 5000 | AG10: =IF(DATALOG!AG658=0,"",DATALOG!AG658) -> 11 | AH10: =IF(DATALOG!AH658=0,"",DATALOG!AH658) -> 4782 | AI10: =IF(DATALOG!AI658=0,"",DATALOG!AI658) -> 10 | AJ10: =IF(DATALOG!AJ658=0,"",DATALOG!AJ658) -> 2800 | AL10: =IF(DATALOG!AL658=0,"",DATALOG!AL658) -> 16 | AM10: =IF(DATALOG!AM658=0,"",DATALOG!AM658) -> 4500 | AN10: =IF(DATALOG!AN658=0,"",DATALOG!AN658) -> 12 | AO10: =IF(DATALOG!AO658=0,"",DATALOG!AO658) -> 7000 | AP10: =IF(DATALOG!AP658=0,"",DATALOG!AP658) -> 20 | AQ10: =IF(DATALOG!AQ658=0,"",DATALOG!AQ658) -> 2797 | AS10: =IF(DATALOG!AS658=0,"",DATALOG!AS658) -> 17 | AT10: =IF(DATALOG!AT658=0,"",DATALOG!AT658) -> 10000 | AU10: =IF(DATALOG!AU658=0,"",DATALOG!AU658) -> 16 | AV10: =IF(DATALOG!AV658=0,"",DATALOG!AV658) -> 2800 | AW10: =IF(DATALOG!AW658=0,"",DATALOG!AW658) -> 16 | AX10: =IF(DATALOG!AX658=0,"",DATALOG!AX658) -> 1500 | AZ10: =IF(DATALOG!AZ658=0,"",DATALOG!AZ658) | BA10: =IF(DATALOG!BA658=0,"",DATALOG!BA658) | BB10: =IF(DATALOG!BB658=0,"",DATALOG!BB658) | BC10: =IF(DATALOG!BC658=0,"",DATALOG!BC658) | BD10: =IF(DATALOG!BD658=0,"",DATALOG!BD658) | BE10: =IF(DATALOG!BE658=0,"",DATALOG!BE658) | BG10: =IF(DATALOG!BG658=0,"",DATALOG!BG658) | BH10: =IF(DATALOG!BH658=0,"",DATALOG!BH658) | BI10: =IF(DATALOG!BI658=0,"",DATALOG!BI658) | BJ10: =IF(DATALOG!BJ658=0,"",DATALOG!BJ658) | BK10: =IF(DATALOG!BK658=0,"",DATALOG!BK658) | BL10: =IF(DATALOG!BL658=0,"",DATALOG!BL658)
C11: =IF(DATALOG!C659=0,"",DATALOG!C659) -> 16 | D11: =IF(DATALOG!D659=0,"",DATALOG!D659) -> 8125 | E11: =IF(DATALOG!E659=0,"",DATALOG!E659) -> 17 | F11: =IF(DATALOG!F659=0,"",DATALOG!F659) -> 3790 | G11: =IF(DATALOG!G659=0,"",DATALOG!G659) -> 12 | H11: =IF(DATALOG!H659=0,"",DATALOG!H659) -> 5250 | I11: =IF(DATALOG!I659=0,"",DATALOG!I659) | J11: =IF(DATALOG!J659=0,"",DATALOG!J659) -> 15 | ... O11: =IF(DATALOG!O659=0,"",DATALOG!O659) -> 4350 | Q11: =IF(DATALOG!Q659=0,"",DATALOG!Q659) -> 17 | R11: =IF(DATALOG!R659=0,"",DATALOG!R659) -> 20000 | S11: =IF(DATALOG!S659=0,"",DATALOG!S659) -> 14 | T11: =IF(DATALOG!T659=0,"",DATALOG!T659) -> 4770 | U11: =IF(DATALOG!U659=0,"",DATALOG!U659) -> 16 | V11: =IF(DATALOG!V659=0,"",DATALOG!V659) -> 3718 | X11: =IF(DATALOG!X659=0,"",DATALOG!X659) -> 18 | Y11: =IF(DATALOG!Y659=0,"",DATALOG!Y659) -> 3699 | Z11: =IF(DATALOG!Z659=0,"",DATALOG!Z659) -> 13 | AA11: =IF(DATALOG!AA659=0,"",DATALOG!AA659) -> 5129 | AB11: =IF(DATALOG!AB659=0,"",DATALOG!AB659) -> 14 | AC11: =IF(DATALOG!AC659=0,"",DATALOG!AC659) -> 8020 | AE11: =IF(DATALOG!AE659=0,"",DATALOG!AE659) -> 14 | AF11: =IF(DATALOG!AF659=0,"",DATALOG!AF659) -> 7100 | AG11: =IF(DATALOG!AG659=0,"",DATALOG!AG659) -> 12 | AH11: =IF(DATALOG!AH659=0,"",DATALOG!AH659) -> 6000 | AI11: =IF(DATALOG!AI659=0,"",DATALOG!AI659) -> 11 | AJ11: =IF(DATALOG!AJ659=0,"",DATALOG!AJ659) -> 5782 | AL11: =IF(DATALOG!AL659=0,"",DATALOG!AL659) -> 17 | AM11: =IF(DATALOG!AM659=0,"",DATALOG!AM659) -> 5000 | AN11: =IF(DATALOG!AN659=0,"",DATALOG!AN659) -> 16 | AO11: =IF(DATALOG!AO659=0,"",DATALOG!AO659) -> 2800 | AP11: =IF(DATALOG!AP659=0,"",DATALOG!AP659) -> 21 | AQ11: =IF(DATALOG!AQ659=0,"",DATALOG!AQ659) -> 8779 | AS11: =IF(DATALOG!AS659=0,"",DATALOG!AS659) -> 18 | AT11: =IF(DATALOG!AT659=0,"",DATALOG!AT659) -> 2666 | AU11: =IF(DATALOG!AU659=0,"",DATALOG!AU659) -> 38 | AV11: =IF(DATALOG!AV659=0,"",DATALOG!AV659) -> 11294 | AW11: =IF(DATALOG!AW659=0,"",DATALOG!AW659) -> 18 | AX11: =IF(DATALOG!AX659=0,"",DATALOG!AX659) -> 9000 | AZ11: =IF(DATALOG!AZ659=0,"",DATALOG!AZ659) | BA11: =IF(DATALOG!BA659=0,"",DATALOG!BA659) | BB11: =IF(DATALOG!BB659=0,"",DATALOG!BB659) | BC11: =IF(DATALOG!BC659=0,"",DATALOG!BC659) | BD11: =IF(DATALOG!BD659=0,"",DATALOG!BD659) | BE11: =IF(DATALOG!BE659=0,"",DATALOG!BE659) | BG11: =IF(DATALOG!BG659=0,"",DATALOG!BG659) | BH11: =IF(DATALOG!BH659=0,"",DATALOG!BH659) | BI11: =IF(DATALOG!BI659=0,"",DATALOG!BI659) | BJ11: =IF(DATALOG!BJ659=0,"",DATALOG!BJ659) | BK11: =IF(DATALOG!BK659=0,"",DATALOG!BK659) | BL11: =IF(DATALOG!BL659=0,"",DATALOG!BL659)
C12: =IF(DATALOG!C660=0,"",DATALOG!C660) -> 17 | D12: =IF(DATALOG!D660=0,"",DATALOG!D660) -> 8001 | E12: =IF(DATALOG!E660=0,"",DATALOG!E660) -> 18 | F12: =IF(DATALOG!F660=0,"",DATALOG!F660) -> 1500 | G12: =IF(DATALOG!G660=0,"",DATALOG!G660) -> 13 | H12: =IF(DATALOG!H660=0,"",DATALOG!H660) -> 4000 | I12: =IF(DATALOG!I660=0,"",DATALOG!I660) | J12: =IF(DATALOG!J660=0,"",DATALOG!J660) -> 16 | ... O12: =IF(DATALOG!O660=0,"",DATALOG!O660) -> 5400 | Q12: =IF(DATALOG!Q660=0,"",DATALOG!Q660) -> 18 | R12: =IF(DATALOG!R660=0,"",DATALOG!R660) -> 7851 | S12: =IF(DATALOG!S660=0,"",DATALOG!S660) -> 16 | T12: =IF(DATALOG!T660=0,"",DATALOG!T660) -> 6822 | U12: =IF(DATALOG!U660=0,"",DATALOG!U660) -> 17 | V12: =IF(DATALOG!V660=0,"",DATALOG!V660) -> 1525 | X12: =IF(DATALOG!X660=0,"",DATALOG!X660) -> 19 | Y12: =IF(DATALOG!Y660=0,"",DATALOG!Y660) -> 3300 | Z12: =IF(DATALOG!Z660=0,"",DATALOG!Z660) -> 14 | AA12: =IF(DATALOG!AA660=0,"",DATALOG!AA660) -> 5601 | AB12: =IF(DATALOG!AB660=0,"",DATALOG!AB660) -> 15 | AC12: =IF(DATALOG!AC660=0,"",DATALOG!AC660) -> 16875 | AE12: =IF(DATALOG!AE660=0,"",DATALOG!AE660) -> 15 | AF12: =IF(DATALOG!AF660=0,"",DATALOG!AF660) -> 7299 | AG12: =IF(DATALOG!AG660=0,"",DATALOG!AG660) -> 13 | AH12: =IF(DATALOG!AH660=0,"",DATALOG!AH660) -> 5329 | AI12: =IF(DATALOG!AI660=0,"",DATALOG!AI660) -> 12 | AJ12: =IF(DATALOG!AJ660=0,"",DATALOG!AJ660) -> 6200 | AL12: =IF(DATALOG!AL660=0,"",DATALOG!AL660) -> 18 | AM12: =IF(DATALOG!AM660=0,"",DATALOG!AM660) -> 5397 | AN12: =IF(DATALOG!AN660=0,"",DATALOG!AN660) -> 21 | AO12: =IF(DATALOG!AO660=0,"",DATALOG!AO660) -> 7500 | AP12: =IF(DATALOG!AP660=0,"",DATALOG!AP660) -> 22 | AQ12: =IF(DATALOG!AQ660=0,"",DATALOG!AQ660) -> 15000 | AS12: =IF(DATALOG!AS660=0,"",DATALOG!AS660) -> 19 | AT12: =IF(DATALOG!AT660=0,"",DATALOG!AT660) -> 3000 | AU12: =IF(DATALOG!AU660=0,"",DATALOG!AU660) -> 39 | AV12: =IF(DATALOG!AV660=0,"",DATALOG!AV660) -> 8600 | AW12: =IF(DATALOG!AW660=0,"",DATALOG!AW660) -> 19 | AX12: =IF(DATALOG!AX660=0,"",DATALOG!AX660) -> 11250 | AZ12: =IF(DATALOG!AZ660=0,"",DATALOG!AZ660) | BA12: =IF(DATALOG!BA660=0,"",DATALOG!BA660) | BB12: =IF(DATALOG!BB660=0,"",DATALOG!BB660) | BC12: =IF(DATALOG!BC660=0,"",DATALOG!BC660) | BD12: =IF(DATALOG!BD660=0,"",DATALOG!BD660) | BE12: =IF(DATALOG!BE660=0,"",DATALOG!BE660) | BG12: =IF(DATALOG!BG660=0,"",DATALOG!BG660) | BH12: =IF(DATALOG!BH660=0,"",DATALOG!BH660) | BI12: =IF(DATALOG!BI660=0,"",DATALOG!BI660) | BJ12: =IF(DATALOG!BJ660=0,"",DATALOG!BJ660) | BK12: =IF(DATALOG!BK660=0,"",DATALOG!BK660) | BL12: =IF(DATALOG!BL660=0,"",DATALOG!BL660)
C13: =IF(DATALOG!C661=0,"",DATALOG!C661) -> 18 | D13: =IF(DATALOG!D661=0,"",DATALOG!D661) -> 3699 | E13: =IF(DATALOG!E661=0,"",DATALOG!E661) -> 20 | F13: =IF(DATALOG!F661=0,"",DATALOG!F661) -> 6788 | G13: =IF(DATALOG!G661=0,"",DATALOG!G661) -> 14 | H13: =IF(DATALOG!H661=0,"",DATALOG!H661) -> 10125 | I13: =IF(DATALOG!I661=0,"",DATALOG!I661) | J13: =IF(DATALOG!J661=0,"",DATALOG!J661) -> 17 | ... O13: =IF(DATALOG!O661=0,"",DATALOG!O661) -> 8100 | Q13: =IF(DATALOG!Q661=0,"",DATALOG!Q661) -> 19 | R13: =IF(DATALOG!R661=0,"",DATALOG!R661) -> 3149 | S13: =IF(DATALOG!S661=0,"",DATALOG!S661) -> 17 | T13: =IF(DATALOG!T661=0,"",DATALOG!T661) -> 1911 | U13: =IF(DATALOG!U661=0,"",DATALOG!U661) -> 18 | V13: =IF(DATALOG!V661=0,"",DATALOG!V661) -> 13287 | X13: =IF(DATALOG!X661=0,"",DATALOG!X661) -> 21 | Y13: =IF(DATALOG!Y661=0,"",DATALOG!Y661) -> 12001 | Z13: =IF(DATALOG!Z661=0,"",DATALOG!Z661) -> 15 | AA13: =IF(DATALOG!AA661=0,"",DATALOG!AA661) -> 15000 | AB13: =IF(DATALOG!AB661=0,"",DATALOG!AB661) -> 16 | AC13: =IF(DATALOG!AC661=0,"",DATALOG!AC661) -> 1500 | AE13: =IF(DATALOG!AE661=0,"",DATALOG!AE661) -> 16 | AF13: =IF(DATALOG!AF661=0,"",DATALOG!AF661) -> 5500 | AG13: =IF(DATALOG!AG661=0,"",DATALOG!AG661) -> 14 | AH13: =IF(DATALOG!AH661=0,"",DATALOG!AH661) -> 7580 | AI13: =IF(DATALOG!AI661=0,"",DATALOG!AI661) -> 13 | AJ13: =IF(DATALOG!AJ661=0,"",DATALOG!AJ661) -> 4620 | AL13: =IF(DATALOG!AL661=0,"",DATALOG!AL661) -> 20 | AM13: =IF(DATALOG!AM661=0,"",DATALOG!AM661) -> 10000 | AN13: =IF(DATALOG!AN661=0,"",DATALOG!AN661) -> 22 | AO13: =IF(DATALOG!AO661=0,"",DATALOG!AO661) -> 13765 | AP13: =IF(DATALOG!AP661=0,"",DATALOG!AP661) -> 23 | AQ13: =IF(DATALOG!AQ661=0,"",DATALOG!AQ661) -> 4120 | AS13: =IF(DATALOG!AS661=0,"",DATALOG!AS661) -> 20 | AT13: =IF(DATALOG!AT661=0,"",DATALOG!AT661) -> 15000 | AU13: =IF(DATALOG!AU661=0,"",DATALOG!AU661) -> 53 | AV13: =IF(DATALOG!AV661=0,"",DATALOG!AV661) -> 3570 | AW13: =IF(DATALOG!AW661=0,"",DATALOG!AW661) -> 20 | AX13: =IF(DATALOG!AX661=0,"",DATALOG!AX661) -> 4173 | AZ13: =IF(DATALOG!AZ661=0,"",DATALOG!AZ661) | BA13: =IF(DATALOG!BA661=0,"",DATALOG!BA661) | BB13: =IF(DATALOG!BB661=0,"",DATALOG!BB661) | BC13: =IF(DATALOG!BC661=0,"",DATALOG!BC661) | BD13: =IF(DATALOG!BD661=0,"",DATALOG!BD661) | BE13: =IF(DATALOG!BE661=0,"",DATALOG!BE661) | BG13: =IF(DATALOG!BG661=0,"",DATALOG!BG661) | BH13: =IF(DATALOG!BH661=0,"",DATALOG!BH661) | BI13: =IF(DATALOG!BI661=0,"",DATALOG!BI661) | BJ13: =IF(DATALOG!BJ661=0,"",DATALOG!BJ661) | BK13: =IF(DATALOG!BK661=0,"",DATALOG!BK661) | BL13: =IF(DATALOG!BL661=0,"",DATALOG!BL661)
C14: =IF(DATALOG!C662=0,"",DATALOG!C662) -> 19 | D14: =IF(DATALOG!D662=0,"",DATALOG!D662) -> 10624 | E14: =IF(DATALOG!E662=0,"",DATALOG!E662) -> 21 | F14: =IF(DATALOG!F662=0,"",DATALOG!F662) -> 1000 | G14: =IF(DATALOG!G662=0,"",DATALOG!G662) -> 16 | H14: =IF(DATALOG!H662=0,"",DATALOG!H662) -> 2500 | I14: =IF(DATALOG!I662=0,"",DATALOG!I662) | J14: =IF(DATALOG!J662=0,"",DATALOG!J662) -> 18 | ... O14: =IF(DATALOG!O662=0,"",DATALOG!O662) -> 2500 | Q14: =IF(DATALOG!Q662=0,"",DATALOG!Q662) -> 24 | R14: =IF(DATALOG!R662=0,"",DATALOG!R662) -> 8736 | S14: =IF(DATALOG!S662=0,"",DATALOG!S662) -> 18 | T14: =IF(DATALOG!T662=0,"",DATALOG!T662) -> 5512 | U14: =IF(DATALOG!U662=0,"",DATALOG!U662) -> 19 | V14: =IF(DATALOG!V662=0,"",DATALOG!V662) -> 19286 | X14: =IF(DATALOG!X662=0,"",DATALOG!X662) -> 23 | Y14: =IF(DATALOG!Y662=0,"",DATALOG!Y662) -> 7098 | Z14: =IF(DATALOG!Z662=0,"",DATALOG!Z662) -> 16 | AA14: =IF(DATALOG!AA662=0,"",DATALOG!AA662) -> 6775 | AB14: =IF(DATALOG!AB662=0,"",DATALOG!AB662) -> 17 | AC14: =IF(DATALOG!AC662=0,"",DATALOG!AC662) -> 1742 | AE14: =IF(DATALOG!AE662=0,"",DATALOG!AE662) -> 17 | AF14: =IF(DATALOG!AF662=0,"",DATALOG!AF662) -> 5000 | AG14: =IF(DATALOG!AG662=0,"",DATALOG!AG662) -> 16 | AH14: =IF(DATALOG!AH662=0,"",DATALOG!AH662) -> 4100 | AI14: =IF(DATALOG!AI662=0,"",DATALOG!AI662) -> 14 | AJ14: =IF(DATALOG!AJ662=0,"",DATALOG!AJ662) -> 8020 | AL14: =IF(DATALOG!AL662=0,"",DATALOG!AL662) -> 23 | AM14: =IF(DATALOG!AM662=0,"",DATALOG!AM662) -> 7683 | AN14: =IF(DATALOG!AN662=0,"",DATALOG!AN662) -> 30 | AO14: =IF(DATALOG!AO662=0,"",DATALOG!AO662) -> 4865 | AP14: =IF(DATALOG!AP662=0,"",DATALOG!AP662) -> 31 | AQ14: =IF(DATALOG!AQ662=0,"",DATALOG!AQ662) -> 4519 | AS14: =IF(DATALOG!AS662=0,"",DATALOG!AS662) -> 65 | AT14: =IF(DATALOG!AT662=0,"",DATALOG!AT662) -> 4000 | AU14: =IF(DATALOG!AU662=0,"",DATALOG!AU662) -> 66 | AV14: =IF(DATALOG!AV662=0,"",DATALOG!AV662) -> 3358 | AW14: =IF(DATALOG!AW662=0,"",DATALOG!AW662) -> 23 | AX14: =IF(DATALOG!AX662=0,"",DATALOG!AX662) -> 3250 | AZ14: =IF(DATALOG!AZ662=0,"",DATALOG!AZ662) | BA14: =IF(DATALOG!BA662=0,"",DATALOG!BA662) | BB14: =IF(DATALOG!BB662=0,"",DATALOG!BB662) | BC14: =IF(DATALOG!BC662=0,"",DATALOG!BC662) | BD14: =IF(DATALOG!BD662=0,"",DATALOG!BD662) | BE14: =IF(DATALOG!BE662=0,"",DATALOG!BE662) | BG14: =IF(DATALOG!BG662=0,"",DATALOG!BG662) | BH14: =IF(DATALOG!BH662=0,"",DATALOG!BH662) | BI14: =IF(DATALOG!BI662=0,"",DATALOG!BI662) | BJ14: =IF(DATALOG!BJ662=0,"",DATALOG!BJ662) | BK14: =IF(DATALOG!BK662=0,"",DATALOG!BK662) | BL14: =IF(DATALOG!BL662=0,"",DATALOG!BL662)
C15: =IF(DATALOG!C663=0,"",DATALOG!C663) -> 20 | D15: =IF(DATALOG!D663=0,"",DATALOG!D663) -> 9000 | E15: =IF(DATALOG!E663=0,"",DATALOG!E663) -> 22 | F15: =IF(DATALOG!F663=0,"",DATALOG!F663) -> 2437 | G15: =IF(DATALOG!G663=0,"",DATALOG!G663) -> 17 | H15: =IF(DATALOG!H663=0,"",DATALOG!H663) -> 9779 | I15: =IF(DATALOG!I663=0,"",DATALOG!I663) | J15: =IF(DATALOG!J663=0,"",DATALOG!J663) -> 19 | ... O15: =IF(DATALOG!O663=0,"",DATALOG!O663) -> 8511 | Q15: =IF(DATALOG!Q663=0,"",DATALOG!Q663) -> 27 | R15: =IF(DATALOG!R663=0,"",DATALOG!R663) -> 2545 | S15: =IF(DATALOG!S663=0,"",DATALOG!S663) -> 19 | T15: =IF(DATALOG!T663=0,"",DATALOG!T663) -> 21428 | U15: =IF(DATALOG!U663=0,"",DATALOG!U663) -> 20 | V15: =IF(DATALOG!V663=0,"",DATALOG!V663) -> 11257 | X15: =IF(DATALOG!X663=0,"",DATALOG!X663) -> 28 | Y15: =IF(DATALOG!Y663=0,"",DATALOG!Y663) -> 14523 | Z15: =IF(DATALOG!Z663=0,"",DATALOG!Z663) -> 17 | AA15: =IF(DATALOG!AA663=0,"",DATALOG!AA663) -> 2615 | AB15: =IF(DATALOG!AB663=0,"",DATALOG!AB663) -> 20 | AC15: =IF(DATALOG!AC663=0,"",DATALOG!AC663) -> 10000 | AE15: =IF(DATALOG!AE663=0,"",DATALOG!AE663) -> 18 | AF15: =IF(DATALOG!AF663=0,"",DATALOG!AF663) -> 2704 | AG15: =IF(DATALOG!AG663=0,"",DATALOG!AG663) -> 17 | AH15: =IF(DATALOG!AH663=0,"",DATALOG!AH663) -> 5778 | AI15: =IF(DATALOG!AI663=0,"",DATALOG!AI663) -> 15 | AJ15: =IF(DATALOG!AJ663=0,"",DATALOG!AJ663) -> 11250 | AL15: =IF(DATALOG!AL663=0,"",DATALOG!AL663) -> 27 | AM15: =IF(DATALOG!AM663=0,"",DATALOG!AM663) -> 4168 | AN15: =IF(DATALOG!AN663=0,"",DATALOG!AN663) -> 31 | AO15: =IF(DATALOG!AO663=0,"",DATALOG!AO663) -> 10 | AP15: =IF(DATALOG!AP663=0,"",DATALOG!AP663) -> 32 | AQ15: =IF(DATALOG!AQ663=0,"",DATALOG!AQ663) -> 6000 | AS15: =IF(DATALOG!AS663=0,"",DATALOG!AS663) -> 66 | AT15: =IF(DATALOG!AT663=0,"",DATALOG!AT663) -> 14250 | AU15: =IF(DATALOG!AU663=0,"",DATALOG!AU663) -> 67 | AV15: =IF(DATALOG!AV663=0,"",DATALOG!AV663) -> 5237 | AW15: =IF(DATALOG!AW663=0,"",DATALOG!AW663) -> 35 | AX15: =IF(DATALOG!AX663=0,"",DATALOG!AX663) -> 11334 | AZ15: =IF(DATALOG!AZ663=0,"",DATALOG!AZ663) | BA15: =IF(DATALOG!BA663=0,"",DATALOG!BA663) | BB15: =IF(DATALOG!BB663=0,"",DATALOG!BB663) | BC15: =IF(DATALOG!BC663=0,"",DATALOG!BC663) | BD15: =IF(DATALOG!BD663=0,"",DATALOG!BD663) | BE15: =IF(DATALOG!BE663=0,"",DATALOG!BE663) | BG15: =IF(DATALOG!BG663=0,"",DATALOG!BG663) | BH15: =IF(DATALOG!BH663=0,"",DATALOG!BH663) | BI15: =IF(DATALOG!BI663=0,"",DATALOG!BI663) | BJ15: =IF(DATALOG!BJ663=0,"",DATALOG!BJ663) | BK15: =IF(DATALOG!BK663=0,"",DATALOG!BK663) | BL15: =IF(DATALOG!BL663=0,"",DATALOG!BL663)
C16: =IF(DATALOG!C664=0,"",DATALOG!C664) -> 21 | D16: =IF(DATALOG!D664=0,"",DATALOG!D664) -> 13375 | E16: =IF(DATALOG!E664=0,"",DATALOG!E664) -> 29 | F16: =IF(DATALOG!F664=0,"",DATALOG!F664) -> 13125 | G16: =IF(DATALOG!G664=0,"",DATALOG!G664) -> 18 | H16: =IF(DATALOG!H664=0,"",DATALOG!H664) -> 8437 | I16: =IF(DATALOG!I664=0,"",DATALOG!I664) | J16: =IF(DATALOG!J664=0,"",DATALOG!J664) -> 23 | ... O16: =IF(DATALOG!O664=0,"",DATALOG!O664) -> 6750 | Q16: =IF(DATALOG!Q664=0,"",DATALOG!Q664) -> 32 | R16: =IF(DATALOG!R664=0,"",DATALOG!R664) -> 33962 | S16: =IF(DATALOG!S664=0,"",DATALOG!S664) -> 20 | T16: =IF(DATALOG!T664=0,"",DATALOG!T664) -> 12428 | U16: =IF(DATALOG!U664=0,"",DATALOG!U664) -> 23 | V16: =IF(DATALOG!V664=0,"",DATALOG!V664) -> 5715 | X16: =IF(DATALOG!X664=0,"",DATALOG!X664) -> 33 | Y16: =IF(DATALOG!Y664=0,"",DATALOG!Y664) -> 3500 | Z16: =IF(DATALOG!Z664=0,"",DATALOG!Z664) -> 18 | AA16: =IF(DATALOG!AA664=0,"",DATALOG!AA664) -> 6163 | AB16: =IF(DATALOG!AB664=0,"",DATALOG!AB664) -> 21 | AC16: =IF(DATALOG!AC664=0,"",DATALOG!AC664) -> 2741 | AE16: =IF(DATALOG!AE664=0,"",DATALOG!AE664) -> 19 | AF16: =IF(DATALOG!AF664=0,"",DATALOG!AF664) -> 2000 | AG16: =IF(DATALOG!AG664=0,"",DATALOG!AG664) -> 18 | AH16: =IF(DATALOG!AH664=0,"",DATALOG!AH664) -> 7567 | AI16: =IF(DATALOG!AI664=0,"",DATALOG!AI664) -> 16 | AJ16: =IF(DATALOG!AJ664=0,"",DATALOG!AJ664) -> 1897 | AL16: =IF(DATALOG!AL664=0,"",DATALOG!AL664) -> 28 | AM16: =IF(DATALOG!AM664=0,"",DATALOG!AM664) -> 11129 | AN16: =IF(DATALOG!AN664=0,"",DATALOG!AN664) -> 34 | AO16: =IF(DATALOG!AO664=0,"",DATALOG!AO664) -> 7500 | AP16: =IF(DATALOG!AP664=0,"",DATALOG!AP664) -> 35 | AQ16: =IF(DATALOG!AQ664=0,"",DATALOG!AQ664) -> 5671 | AS16: =IF(DATALOG!AS664=0,"",DATALOG!AS664) -> 68 | AT16: =IF(DATALOG!AT664=0,"",DATALOG!AT664) -> 9703 | AU16: =IF(DATALOG!AU664=0,"",DATALOG!AU664) -> 68 | AV16: =IF(DATALOG!AV664=0,"",DATALOG!AV664) -> 6000 | AW16: =IF(DATALOG!AW664=0,"",DATALOG!AW664) -> 46 | AX16: =IF(DATALOG!AX664=0,"",DATALOG!AX664) -> 1546 | AZ16: =IF(DATALOG!AZ664=0,"",DATALOG!AZ664) | BA16: =IF(DATALOG!BA664=0,"",DATALOG!BA664) | BB16: =IF(DATALOG!BB664=0,"",DATALOG!BB664) | BC16: =IF(DATALOG!BC664=0,"",DATALOG!BC664) | BD16: =IF(DATALOG!BD664=0,"",DATALOG!BD664) | BE16: =IF(DATALOG!BE664=0,"",DATALOG!BE664) | BG16: =IF(DATALOG!BG664=0,"",DATALOG!BG664) | BH16: =IF(DATALOG!BH664=0,"",DATALOG!BH664) | BI16: =IF(DATALOG!BI664=0,"",DATALOG!BI664) | BJ16: =IF(DATALOG!BJ664=0,"",DATALOG!BJ664) | BK16: =IF(DATALOG!BK664=0,"",DATALOG!BK664) | BL16: =IF(DATALOG!BL664=0,"",DATALOG!BL664)
... C1003: =IF(DATALOG!C1651=0,"",DATALOG!C1651) | D1003: =IF(DATALOG!D1651=0,"",DATALOG!D1651) | E1003: =IF(DATALOG!E1651=0,"",DATALOG!E1651) | F1003: =IF(DATALOG!F1651=0,"",DATALOG!F1651) | G1003: =IF(DATALOG!G1651=0,"",DATALOG!G1651) | H1003: =IF(DATALOG!H1651=0,"",DATALOG!H1651) | I1003: =IF(DATALOG!I1651=0,"",DATALOG!I1651) | J1003: =IF(DATALOG!J1651=0,"",DATALOG!J1651) | ... O1003: =IF(DATALOG!O1651=0,"",DATALOG!O1651) | Q1003: =IF(DATALOG!Q1651=0,"",DATALOG!Q1651) | R1003: =IF(DATALOG!R1651=0,"",DATALOG!R1651) | S1003: =IF(DATALOG!S1651=0,"",DATALOG!S1651) | T1003: =IF(DATALOG!T1651=0,"",DATALOG!T1651) | U1003: =IF(DATALOG!U1651=0,"",DATALOG!U1651) | V1003: =IF(DATALOG!V1651=0,"",DATALOG!V1651) | X1003: =IF(DATALOG!X1651=0,"",DATALOG!X1651) | Y1003: =IF(DATALOG!Y1651=0,"",DATALOG!Y1651) | Z1003: =IF(DATALOG!Z1651=0,"",DATALOG!Z1651) | AA1003: =IF(DATALOG!AA1651=0,"",DATALOG!AA1651) | AB1003: =IF(DATALOG!AB1651=0,"",DATALOG!AB1651) | AC1003: =IF(DATALOG!AC1651=0,"",DATALOG!AC1651) | AE1003: =IF(DATALOG!AE1651=0,"",DATALOG!AE1651) | AF1003: =IF(DATALOG!AF1651=0,"",DATALOG!AF1651) | AG1003: =IF(DATALOG!AG1651=0,"",DATALOG!AG1651) | AH1003: =IF(DATALOG!AH1651=0,"",DATALOG!AH1651) | AI1003: =IF(DATALOG!AI1651=0,"",DATALOG!AI1651) | AJ1003: =IF(DATALOG!AJ1651=0,"",DATALOG!AJ1651) | AL1003: =IF(DATALOG!AL1651=0,"",DATALOG!AL1651) | AM1003: =IF(DATALOG!AM1651=0,"",DATALOG!AM1651) | AN1003: =IF(DATALOG!AN1651=0,"",DATALOG!AN1651) | AO1003: =IF(DATALOG!AO1651=0,"",DATALOG!AO1651) | AP1003: =IF(DATALOG!AP1651=0,"",DATALOG!AP1651) | AQ1003: =IF(DATALOG!AQ1651=0,"",DATALOG!AQ1651) | AS1003: =IF(DATALOG!AS1651=0,"",DATALOG!AS1651) | AT1003: =IF(DATALOG!AT1651=0,"",DATALOG!AT1651) | AU1003: =IF(DATALOG!AU1651=0,"",DATALOG!AU1651) | AV1003: =IF(DATALOG!AV1651=0,"",DATALOG!AV1651) | AW1003: =IF(DATALOG!AW1651=0,"",DATALOG!AW1651) | AX1003: =IF(DATALOG!AX1651=0,"",DATALOG!AX1651) | AZ1003: =IF(DATALOG!AZ1651=0,"",DATALOG!AZ1651) | BA1003: =IF(DATALOG!BA1651=0,"",DATALOG!BA1651) | BB1003: =IF(DATALOG!BB1651=0,"",DATALOG!BB1651) | BC1003: =IF(DATALOG!BC1651=0,"",DATALOG!BC1651) | BD1003: =IF(DATALOG!BD1651=0,"",DATALOG!BD1651) | BE1003: =IF(DATALOG!BE1651=0,"",DATALOG!BE1651) | BG1003: =IF(DATALOG!BG1651=0,"",DATALOG!BG1651) | BH1003: =IF(DATALOG!BH1651=0,"",DATALOG!BH1651) | BI1003: =IF(DATALOG!BI1651=0,"",DATALOG!BI1651) | BJ1003: =IF(DATALOG!BJ1651=0,"",DATALOG!BJ1651) | BK1003: =IF(DATALOG!BK1651=0,"",DATALOG!BK1651) | BL1003: =IF(DATALOG!BL1651=0,"",DATALOG!BL1651)

Sheet Inventario Empresas Linea 2
C2: =UPPER(DATALOG!B1652) -> EMPRESAS CON INVENTARIO ELECTRODOMES
C3: =IF(DATALOG!C1652="","",DATALOG!C1652) -> Alemania | D3: =IF(DATALOG!D1652="","",DATALOG!D1652) -> Alemania | E3: =IF(DATALOG!E1652="","",DATALOG!E1652) -> Australia | F3: =IF(DATALOG!F1652="","",DATALOG!F1652) -> Australia | G3: =IF(DATALOG!G1652="","",DATALOG!G1652) -> Espana | H3: =IF(DATALOG!H1652="","",DATALOG!H1652) -> Espana | I3: =IF(DATALOG!I1652="","",DATALOG!I1652) | J3: =IF(DATALOG!J1652="","",DATALOG!J1652) -> Alemania | ... BL3: =IF(DATALOG!BL1652="","",DATALOG!BL1652)
C4: =IF(DATALOG!C1653="","",DATALOG!C1653) -> Hervidor | D4: =IF(DATALOG!D1653="","",DATALOG!D1653) -> Inventario | E4: =IF(DATALOG!E1653="","",DATALOG!E1653) -> Hervidor | F4: =IF(DATALOG!F1653="","",DATALOG!F1653) -> Inventario | G4: =IF(DATALOG!G1653="","",DATALOG!G1653) -> Hervidor | H4: =IF(DATALOG!H1653="","",DATALOG!H1653) -> Inventario | I4: =IF(DATALOG!I1653="","",DATALOG!I1653) | J4: =IF(DATALOG!J1653="","",DATALOG!J1653) -> Tostador | ... BL4: =IF(DATALOG!BL1653="","",DATALOG!BL1653)
C5: =IF(DATALOG!C1654=0,"",DATALOG!C1654) -> 2 | D5: =IF(DATALOG!D1654=0,"",DATALOG!D1654) -> 2000 | E5: =IF(DATALOG!E1654=0,"",DATALOG!E1654) -> 4 | F5: =IF(DATALOG!F1654=0,"",DATALOG!F1654) -> 5000 | G5: =IF(DATALOG!G1654=0,"",DATALOG!G1654) -> 2 | H5: =IF(DATALOG!H1654=0,"",DATALOG!H1654) -> 5000 | I5: =IF(DATALOG!I1654=0,"",DATALOG!I1654) | J5: =IF(DATALOG!J1654=0,"",DATALOG!J1654) -> 2 | ... BL5: =IF(DATALOG!BL1654=0,"",DATALOG!BL1654)
C6: =IF(DATALOG!C1655=0,"",DATALOG!C1655) -> 7 | D6: =IF(DATALOG!D1655=0,"",DATALOG!D1655) -> 4846 | E6: =IF(DATALOG!E1655=0,"",DATALOG!E1655) -> 6 | F6: =IF(DATALOG!F1655=0,"",DATALOG!F1655) -> 11742 | G6: =IF(DATALOG!G1655=0,"",DATALOG!G1655) -> 4 | H6: =IF(DATALOG!H1655=0,"",DATALOG!H1655) -> 2713 | I6: =IF(DATALOG!I1655=0,"",DATALOG!I1655) | J6: =IF(DATALOG!J1655=0,"",DATALOG!J1655) -> 3 | ... BL6: =IF(DATALOG!BL1655=0,"",DATALOG!BL1655)
C7: =IF(DATALOG!C1656=0,"",DATALOG!C1656) -> 10 | D7: =IF(DATALOG!D1656=0,"",DATALOG!D1656) -> 6500 | E7: =IF(DATALOG!E1656=0,"",DATALOG!E1656) -> 10 | F7: =IF(DATALOG!F1656=0,"",DATALOG!F1656) -> 2412 | G7: =IF(DATALOG!G1656=0,"",DATALOG!G1656) -> 6 | H7: =IF(DATALOG!H1656=0,"",DATALOG!H1656) -> 15000 | I7: =IF(DATALOG!I1656=0,"",DATALOG!I1656) | J7: =IF(DATALOG!J1656=0,"",DATALOG!J1656) -> 7 | ... BL7: =IF(DATALOG!BL1656=0,"",DATALOG!BL1656)
C8: =IF(DATALOG!C1657=0,"",DATALOG!C1657) -> 12 | D8: =IF(DATALOG!D1657=0,"",DATALOG!D1657) -> 10136 | E8: =IF(DATALOG!E1657=0,"",DATALOG!E1657) -> 11 | F8: =IF(DATALOG!F1657=0,"",DATALOG!F1657) -> 7000 | G8: =IF(DATALOG!G1657=0,"",DATALOG!G1657) -> 7 | H8: =IF(DATALOG!H1657=0,"",DATALOG!H1657) -> 14242 | I8: =IF(DATALOG!I1657=0,"",DATALOG!I1657) | J8: =IF(DATALOG!J1657=0,"",DATALOG!J1657) -> 10 | ... BL8: =IF(DATALOG!BL1657=0,"",DATALOG!BL1657)
C9: =IF(DATALOG!C1658=0,"",DATALOG!C1658) -> 13 | D9: =IF(DATALOG!D1658=0,"",DATALOG!D1658) -> 7185 | E9: =IF(DATALOG!E1658=0,"",DATALOG!E1658) -> 12 | F9: =IF(DATALOG!F1658=0,"",DATALOG!F1658) -> 9612 | G9: =IF(DATALOG!G1658=0,"",DATALOG!G1658) -> 8 | H9: =IF(DATALOG!H1658=0,"",DATALOG!H1658) -> 15000 | I9: =IF(DATALOG!I1658=0,"",DATALOG!I1658) | J9: =IF(DATALOG!J1658=0,"",DATALOG!J1658) -> 12 | ... BL9: =IF(DATALOG!BL1658=0,"",DATALOG!BL1658)
C10: =IF(DATALOG!C1659=0,"",DATALOG!C1659) -> 14 | D10: =IF(DATALOG!D1659=0,"",DATALOG!D1659) -> 9250 | E10: =IF(DATALOG!E1659=0,"",DATALOG!E1659) -> 14 | F10: =IF(DATALOG!F1659=0,"",DATALOG!F1659) -> 7105 | G10: =IF(DATALOG!G1659=0,"",DATALOG!G1659) -> 11 | H10: =IF(DATALOG!H1659=0,"",DATALOG!H1659) -> 7100 | I10: =IF(DATALOG!I1659=0,"",DATALOG!I1659) | J10: =IF(DATALOG!J1659=0,"",DATALOG!J1659) -> 13 | ... BL10: =IF(DATALOG!BL1659=0,"",DATALOG!BL1659)
C11: =IF(DATALOG!C1660=0,"",DATALOG!C1660) -> 15 | D11: =IF(DATALOG!D1660=0,"",DATALOG!D1660) -> 19739 | E11: =IF(DATALOG!E1660=0,"",DATALOG!E1660) -> 16 | F11: =IF(DATALOG!F1660=0,"",DATALOG!F1660) -> 9500 | G11: =IF(DATALOG!G1660=0,"",DATALOG!G1660) -> 12 | H11: =IF(DATALOG!H1660=0,"",DATALOG!H1660) -> 7957 | I11: =IF(DATALOG!I1660=0,"",DATALOG!I1660) | J11: =IF(DATALOG!J1660=0,"",DATALOG!J1660) -> 14 | ... BL11: =IF(DATALOG!BL1660=0,"",DATALOG!BL1660)
C12: =IF(DATALOG!C1661=0,"",DATALOG!C1661) -> 16 | D12: =IF(DATALOG!D1661=0,"",DATALOG!D1661) -> 7569 | E12: =IF(DATALOG!E1661=0,"",DATALOG!E1661) -> 17 | F12: =IF(DATALOG!F1661=0,"",DATALOG!F1661) -> 2320 | G12: =IF(DATALOG!G1661=0,"",DATALOG!G1661) -> 13 | H12: =IF(DATALOG!H1661=0,"",DATALOG!H1661) -> 11465 | I12: =IF(DATALOG!I1661=0,"",DATALOG!I1661) | J12: =IF(DATALOG!J1661=0,"",DATALOG!J1661) -> 15 | ... BL12: =IF(DATALOG!BL1661=0,"",DATALOG!BL1661)
C13: =IF(DATALOG!C1662=0,"",DATALOG!C1662) -> 17 | D13: =IF(DATALOG!D1662=0,"",DATALOG!D1662) -> 10000 | E13: =IF(DATALOG!E1662=0,"",DATALOG!E1662) -> 18 | F13: =IF(DATALOG!F1662=0,"",DATALOG!F1662) -> 8000 | G13: =IF(DATALOG!G1662=0,"",DATALOG!G1662) -> 14 | H13: =IF(DATALOG!H1662=0,"",DATALOG!H1662) -> 15000 | I13: =IF(DATALOG!I1662=0,"",DATALOG!I1662) | J13: =IF(DATALOG!J1662=0,"",DATALOG!J1662) -> 16 | ... BL13: =IF(DATALOG!BL1662=0,"",DATALOG!BL1662)
C14: =IF(DATALOG!C1663=0,"",DATALOG!C1663) -> 18 | D14: =IF(DATALOG!D1663=0,"",DATALOG!D1663) -> 6249 | E14: =IF(DATALOG!E1663=0,"",DATALOG!E1663) -> 19 | F14: =IF(DATALOG!F1663=0,"",DATALOG!F1663) -> 31250 | G14: =IF(DATALOG!G1663=0,"",DATALOG!G1663) -> 15 | H14: =IF(DATALOG!H1663=0,"",DATALOG!H1663) -> 8905 | I14: =IF(DATALOG!I1663=0,"",DATALOG!I1663) | J14: =IF(DATALOG!J1663=0,"",DATALOG!J1663) -> 17 | ... BL14: =IF(DATALOG!BL1663=0,"",DATALOG!BL1663)
C15: =IF(DATALOG!C1664=0,"",DATALOG!C1664) -> 19 | D15: =IF(DATALOG!D1664=0,"",DATALOG!D1664) -> 6000 | E15: =IF(DATALOG!E1664=0,"",DATALOG!E1664) -> 20 | F15: =IF(DATALOG!F1664=0,"",DATALOG!F1664) -> 13000 | G15: =IF(DATALOG!G1664=0,"",DATALOG!G1664) -> 16 | H15: =IF(DATALOG!H1664=0,"",DATALOG!H1664) -> 2897 | I15: =IF(DATALOG!I1664=0,"",DATALOG!I1664) | J15: =IF(DATALOG!J1664=0,"",DATALOG!J1664) -> 18 | ... BL15: =IF(DATALOG!BL1664=0,"",DATALOG!BL1664)
C16: =IF(DATALOG!C1665=0,"",DATALOG!C1665) -> 21 | D16: =IF(DATALOG!D1665=0,"",DATALOG!D1665) -> 23654 | E16: =IF(DATALOG!E1665=0,"",DATALOG!E1665) -> 21 | F16: =IF(DATALOG!F1665=0,"",DATALOG!F1665) -> 7000 | G16: =IF(DATALOG!G1665=0,"",DATALOG!G1665) -> 17 | H16: =IF(DATALOG!H1665=0,"",DATALOG!H1665) -> 8056 | I16: =IF(DATALOG!I1665=0,"",DATALOG!I1665) | J16: =IF(DATALOG!J1665=0,"",DATALOG!J1665) -> 19 | ... BL16: =IF(DATALOG!BL1665=0,"",DATALOG!BL1665)
... C1003: =IF(DATALOG!C2652=0,"",DATALOG!C2652) | D1003: =IF(DATALOG!D2652=0,"",DATALOG!D2652) | E1003: =IF(DATALOG!E2652=0,"",DATALOG!E2652) | F1003: =IF(DATALOG!F2652=0,"",DATALOG!F2652) | G1003: =IF(DATALOG!G2652=0,"",DATALOG!G2652) | H1003: =IF(DATALOG!H2652=0,"",DATALOG!H2652) | I1003: =IF(DATALOG!I2652=0,"",DATALOG!I2652) | J1003: =IF(DATALOG!J2652=0,"",DATALOG!J2652) | ... BL1003: =IF(DATALOG!BL2652=0,"",DATALOG!BL2652)

Sheet Manufactura Linea 1
C3: =UPPER(DATALOG!B157) -> INFORME DE PRODUCCION E INVENTARIO
C4: =UPPER(DATALOG!B158) -> COSTO PROMEDIO DE MANUFACTURA PARA CLIMATIZACIO CONSIDERANDO TODA LA INDUSTRIA
C6: =DATALOG!B159 -> Articulo EstufaGas
D7: =DATALOG!C160 -> Alemania | E7: =DATALOG!D160 -> Australia | F7: =DATALOG!E160 -> Espana
C8: =DATALOG!B161 -> Promedio del periodo | D8: =DATALOG!C161 -> 25 | E8: =DATALOG!D161 -> 27.8 | F8: =DATALOG!E161 -> 24.6
C9: =DATALOG!B162 -> Costo minimo para el periodo | D9: =DATALOG!C162 -> 22.8 | E9: =DATALOG!D162 -> 25.4 | F9: =DATALOG!E162 -> 23.2
C10: =DATALOG!B163 -> 0 | D10: =DATALOG!C163 -> 0 | E10: =DATALOG!D163 -> 0 | F10: =DATALOG!E163 -> 0
C11: =DATALOG!B164 -> Total de la produccion (unidades) | D11: =DATALOG!C164 -> 131308 | E11: =DATALOG!D164 -> 127607 | F11: =DATALOG!E164 -> 116749
C12: =DATALOG!B165 -> Turnos producidos | D12: =DATALOG!C165 -> 20 | E12: =DATALOG!D165 -> 19 | F12: =DATALOG!E165 -> 21
C13: =DATALOG!B166 -> Produccion promedio por turno | D13: =DATALOG!C166 -> 6565.4 | E13: =DATALOG!D166 -> 6716.2 | F13: =DATALOG!E166 -> 5559.5
C15: =DATALOG!B168 -> Articulo EstufaElectr
D16: =DATALOG!C169 -> Alemania | E16: =DATALOG!D169 -> Australia | F16: =DATALOG!E169 -> Espana
C17: =DATALOG!B170 -> Promedio del periodo | D17: =DATALOG!C170 -> 31.6 | E17: =DATALOG!D170 -> 36.2 | F17: =DATALOG!E170 -> 33
C18: =DATALOG!B171 -> Costo minimo para el periodo | D18: =DATALOG!C171 -> 28.2 | E18: =DATALOG!D171 -> 32.5 | F18: =DATALOG!E171 -> 30.6
C19: =DATALOG!B172 -> 0 | D19: =DATALOG!C172 -> 0 | E19: =DATALOG!D172 -> 0 | F19: =DATALOG!E172 -> 0
C20: =DATALOG!B173 -> Total de la produccion (unidades) | D20: =DATALOG!C173 -> 128875 | E20: =DATALOG!D173 -> 132590 | F20: =DATALOG!E173 -> 115436
C21: =DATALOG!B174 -> Turnos producidos | D21: =DATALOG!C174 -> 25 | E21: =DATALOG!D174 -> 26 | F21: =DATALOG!E174 -> 26
C22: =DATALOG!B175 -> Produccion promedio por turno | D22: =DATALOG!C175 -> 5155 | E22: =DATALOG!D175 -> 5099.6 | F22: =DATALOG!E175 -> 4439.8
C24: =DATALOG!B177 -> Articulo VentPedestal
D25: =DATALOG!C178 -> Alemania | E25: =DATALOG!D178 -> Australia | F25: =DATALOG!E178 -> Espana
C26: =DATALOG!B179 -> Promedio del periodo | D26: =DATALOG!C179 -> 14.8 | E26: =DATALOG!D179 -> 8.2 | F26: =DATALOG!E179 -> 9.3
C27: =DATALOG!B180 -> Costo minimo para el periodo | D27: =DATALOG!C180 -> 9.1 | E27: =DATALOG!D180 -> 7.8 | F27: =DATALOG!E180 -> 8.7
C28: =DATALOG!B181 -> 0 | D28: =DATALOG!C181 -> 0 | E28: =DATALOG!D181 -> 0 | F28: =DATALOG!E181 -> 0
C29: =DATALOG!B182 -> Total de la produccion (unidades) | D29: =DATALOG!C182 -> 200481 | E29: =DATALOG!D182 -> 99175 | F29: =DATALOG!E182 -> 255734
C30: =DATALOG!B183 -> Turnos producidos | D30: =DATALOG!C183 -> 20 | E30: =DATALOG!D183 -> 10 | F30: =DATALOG!E183 -> 24
C31: =DATALOG!B184 -> Produccion promedio por turno | D31: =DATALOG!C184 -> 10024 | E31: =DATALOG!D184 -> 9917.5 | F31: =DATALOG!E184 -> 10655.6
C33: =DATALOG!B186 -> Articulo Vent_Torre
D34: =DATALOG!C187 -> Alemania | E34: =DATALOG!D187 -> Australia | F34: =DATALOG!E187 -> Espana
C35: =DATALOG!B188 -> Promedio del periodo | D35: =DATALOG!C188 -> 14.9 | E35: =DATALOG!D188 -> 13.9 | F35: =DATALOG!E188 -> 14.6
C36: =DATALOG!B189 -> Costo minimo para el periodo | D36: =DATALOG!C189 -> 14.1 | E36: =DATALOG!D189 -> 12.7 | F36: =DATALOG!E189 -> 13.9
C37: =DATALOG!B190 -> 0 | D37: =DATALOG!C190 -> 0 | E37: =DATALOG!D190 -> 0 | F37: =DATALOG!E190 -> 0
C38: =DATALOG!B191 -> Total de la produccion (unidades) | D38: =DATALOG!C191 -> 253714 | E38: =DATALOG!D191 -> 187502 | F38: =DATALOG!E191 -> 208288
C39: =DATALOG!B192 -> Turnos producidos | D39: =DATALOG!C192 -> 17 | E39: =DATALOG!D192 -> 20 | F39: =DATALOG!E192 -> 26
C40: =DATALOG!B193 -> Produccion promedio por turno | D40: =DATALOG!C193 -> 14924.4 | E40: =DATALOG!D193 -> 9375.1 | F40: =DATALOG!E193 -> 8011.1
C42: =DATALOG!B195 -> Articulo Purif_Aire
D43: =DATALOG!C196 -> Alemania | E43: =DATALOG!D196 -> Australia | F43: =DATALOG!E196 -> Espana
C44: =DATALOG!B197 -> Promedio del periodo | D44: =DATALOG!C197 -> 19.1 | E44: =DATALOG!D197 -> 19.3 | F44: =DATALOG!E197 -> 19.3
C45: =DATALOG!B198 -> Costo minimo para el periodo | D45: =DATALOG!C198 -> 17.2 | E45: =DATALOG!D198 -> 17.1 | F45: =DATALOG!E198 -> 17.9
C46: =DATALOG!B199 -> 0 | D46: =DATALOG!C199 -> 0 | E46: =DATALOG!D199 -> 0 | F46: =DATALOG!E199 -> 0
C47: =DATALOG!B200 -> Total de la produccion (unidades) | D47: =DATALOG!C200 -> 274318 | E47: =DATALOG!D200 -> 148144 | F47: =DATALOG!E200 -> 241266
C48: =DATALOG!B201 -> Turnos producidos | D48: =DATALOG!C201 -> 28 | E48: =DATALOG!D201 -> 22 | F48: =DATALOG!E201 -> 31
C49: =DATALOG!B202 -> Produccion promedio por turno | D49: =DATALOG!C202 -> 9797.1 | E49: =DATALOG!D202 -> 6733.8 | F49: =DATALOG!E202 -> 7782.8
C51: =DATALOG!B204 -> Articulo Deshumidific
D52: =DATALOG!C205 -> Alemania | E52: =DATALOG!D205 -> Australia | F52: =DATALOG!E205 -> Espana
C53: =DATALOG!B206 -> Promedio del periodo | D53: =DATALOG!C206 -> 22.1 | E53: =DATALOG!D206 -> 23.3 | F53: =DATALOG!E206 -> 22
C54: =DATALOG!B207 -> Costo minimo para el periodo | D54: =DATALOG!C207 -> 20.7 | E54: =DATALOG!D207 -> 22.8 | F54: =DATALOG!E207 -> 20.9
C55: =DATALOG!B208 -> 0 | D55: =DATALOG!C208 -> 0 | E55: =DATALOG!D208 -> 0 | F55: =DATALOG!E208 -> 0
C56: =DATALOG!B209 -> Total de la produccion (unidades) | D56: =DATALOG!C209 -> 19500 | E56: =DATALOG!D209 -> 37947 | F56: =DATALOG!E209 -> 54177
C57: =DATALOG!B210 -> Turnos producidos | D57: =DATALOG!C210 -> 3 | E57: =DATALOG!D210 -> 7 | F57: =DATALOG!E210 -> 11
C58: =DATALOG!B211 -> Produccion promedio por turno | D58: =DATALOG!C211 -> 6500 | E58: =DATALOG!D211 -> 5421 | F58: =DATALOG!E211 -> 4925.2
C60: =DATALOG!B213 -> Articulo Ionizador
D61: =DATALOG!C214 -> Alemania | E61: =DATALOG!D214 -> Australia | F61: =DATALOG!E214 -> Espana
C62: =DATALOG!B215 -> Promedio del periodo | D62: =DATALOG!C215 -> 15.1 | E62: =DATALOG!D215 -> 15.5 | F62: =DATALOG!E215 -> 15.4
C63: =DATALOG!B216 -> Costo minimo para el periodo | D63: =DATALOG!C216 -> 14 | E63: =DATALOG!D216 -> 14.7 | F63: =DATALOG!E216 -> 14.6
C64: =DATALOG!B217 -> 0 | D64: =DATALOG!C217 -> 0 | E64: =DATALOG!D217 -> 0 | F64: =DATALOG!E217 -> 0
C65: =DATALOG!B218 -> Total de la produccion (unidades) | D65: =DATALOG!C218 -> 43959 | E65: =DATALOG!D218 -> 51525 | F65: =DATALOG!E218 -> 52467
C66: =DATALOG!B219 -> Turnos producidos | D66: =DATALOG!C219 -> 4 | E66: =DATALOG!D219 -> 5 | F66: =DATALOG!E219 -> 9
C67: =DATALOG!B220 -> Produccion promedio por turno | D67: =DATALOG!C220 -> 10989.8 | E67: =DATALOG!D220 -> 10305 | F67: =DATALOG!E220 -> 5829.7
C69: =DATALOG!B222 -> 0
D70: =DATALOG!C223 -> 0 | E70: =DATALOG!D223 -> 0 | F70: =DATALOG!E223 -> 0
C71: =DATALOG!B224 -> 0 | D71: =DATALOG!C224 -> 0 | E71: =DATALOG!D224 -> 0 | F71: =DATALOG!E224 -> 0
C72: =DATALOG!B225 -> 0 | D72: =DATALOG!C225 -> 0 | E72: =DATALOG!D225 -> 0 | F72: =DATALOG!E225 -> 0
C73: =DATALOG!B226 -> 0 | D73: =DATALOG!C226 -> 0 | E73: =DATALOG!D226 -> 0 | F73: =DATALOG!E226 -> 0
C74: =DATALOG!B227 -> 0 | D74: =DATALOG!C227 -> 0 | E74: =DATALOG!D227 -> 0 | F74: =DATALOG!E227 -> 0
C75: =DATALOG!B228 -> 0 | D75: =DATALOG!C228 -> 0 | E75: =DATALOG!D228 -> 0 | F75: =DATALOG!E228 -> 0
C76: =DATALOG!B229 -> 0 | D76: =DATALOG!C229 -> 0 | E76: =DATALOG!D229 -> 0 | F76: =DATALOG!E229 -> 0
C78: =DATALOG!B231 -> 0
D79: =DATALOG!C232 -> 0 | E79: =DATALOG!D232 -> 0 | F79: =DATALOG!E232 -> 0
C80: =DATALOG!B233 -> 0 | D80: =DATALOG!C233 -> 0 | E80: =DATALOG!D233 -> 0 | F80: =DATALOG!E233 -> 0
C81: =DATALOG!B234 -> 0 | D81: =DATALOG!C234 -> 0 | E81: =DATALOG!D234 -> 0 | F81: =DATALOG!E234 -> 0
C82: =DATALOG!B235 -> 0 | D82: =DATALOG!C235 -> 0 | E82: =DATALOG!D235 -> 0 | F82: =DATALOG!E235 -> 0
C83: =DATALOG!B236 -> 0 | D83: =DATALOG!C236 -> 0 | E83: =DATALOG!D236 -> 0 | F83: =DATALOG!E236 -> 0
C84: =DATALOG!B237 -> 0 | D84: =DATALOG!C237 -> 0 | E84: =DATALOG!D237 -> 0 | F84: =DATALOG!E237 -> 0
C85: =DATALOG!B238 -> 0 | D85: =DATALOG!C238 -> 0 | E85: =DATALOG!D238 -> 0 | F85: =DATALOG!E238 -> 0

Sheet Manufactura Linea 2
C3: =UPPER(DATALOG!B240) -> INFORME DE PRODUCCION E INVENTARIO
C4: =UPPER(DATALOG!B241) -> COSTO PROMEDIO DE MANUFACTURA PARA ELECTRODOMES CONSIDERANDO TODA LA INDUSTRIA
C6: =DATALOG!B242 -> Articulo Hervidor
D7: =DATALOG!C243 -> Alemania | E7: =DATALOG!D243 -> Australia | F7: =DATALOG!E243 -> Espana
C8: =DATALOG!B244 -> Promedio del periodo | D8: =DATALOG!C244 -> 7.1 | E8: =DATALOG!D244 -> 7.7 | F8: =DATALOG!E244 -> 5.8
C9: =DATALOG!B245 -> Costo minimo para el periodo | D9: =DATALOG!C245 -> 5.4 | E9: =DATALOG!D245 -> 7.3 | F9: =DATALOG!E245 -> 5.4
C10: =DATALOG!B246 -> 0 | D10: =DATALOG!C246 -> 0 | E10: =DATALOG!D246 -> 0 | F10: =DATALOG!E246 -> 0
C11: =DATALOG!B247 -> Total de la produccion (unidades) | D11: =DATALOG!C247 -> 207207 | E11: =DATALOG!D247 -> 209172 | F11: =DATALOG!E247 -> 229019
C12: =DATALOG!B248 -> Turnos producidos | D12: =DATALOG!C248 -> 20 | E12: =DATALOG!D248 -> 18 | F12: =DATALOG!E248 -> 24
C13: =DATALOG!B249 -> Produccion promedio por turno | D13: =DATALOG!C249 -> 10360.4 | E13: =DATALOG!D249 -> 11620.7 | F13: =DATALOG!E249 -> 9542.5
C15: =DATALOG!B251 -> Articulo Tostador
D16: =DATALOG!C252 -> Alemania | E16: =DATALOG!D252 -> Australia | F16: =DATALOG!E252 -> Espana
C17: =DATALOG!B253 -> Promedio del periodo | D17: =DATALOG!C253 -> 4.8 | E17: =DATALOG!D253 -> 5.9 | F17: =DATALOG!E253 -> 5.4
C18: =DATALOG!B254 -> Costo minimo para el periodo | D18: =DATALOG!C254 -> 4.5 | E18: =DATALOG!D254 -> 5.8 | F18: =DATALOG!E254 -> 5.1
C19: =DATALOG!B255 -> 0 | D19: =DATALOG!C255 -> 0 | E19: =DATALOG!D255 -> 0 | F19: =DATALOG!E255 -> 0
C20: =DATALOG!B256 -> Total de la produccion (unidades) | D20: =DATALOG!C256 -> 227421 | E20: =DATALOG!D256 -> 195682 | F20: =DATALOG!E256 -> 249303
C21: =DATALOG!B257 -> Turnos producidos | D21: =DATALOG!C257 -> 14 | E21: =DATALOG!D257 -> 17 | F21: =DATALOG!E257 -> 24
C22: =DATALOG!B258 -> Produccion promedio por turno | D22: =DATALOG!C258 -> 16244.4 | E22: =DATALOG!D258 -> 11510.7 | F22: =DATALOG!E258 -> 10387.6
C24: =DATALOG!B260 -> Articulo Batidora
D25: =DATALOG!C261 -> Alemania | E25: =DATALOG!D261 -> Australia | F25: =DATALOG!E261 -> Espana
C26: =DATALOG!B262 -> Promedio del periodo | D26: =DATALOG!C262 -> 3.5 | E26: =DATALOG!D262 -> 4 | F26: =DATALOG!E262 -> 2.9
C27: =DATALOG!B263 -> Costo minimo para el periodo | D27: =DATALOG!C263 -> 3.1 | E27: =DATALOG!D263 -> 3.7 | F27: =DATALOG!E263 -> 2.6
C28: =DATALOG!B264 -> 0 | D28: =DATALOG!C264 -> 0 | E28: =DATALOG!D264 -> 0 | F28: =DATALOG!E264 -> 0
C29: =DATALOG!B265 -> Total de la produccion (unidades) | D29: =DATALOG!C265 -> 279222 | E29: =DATALOG!D265 -> 135020 | F29: =DATALOG!E265 -> 240113
C30: =DATALOG!B266 -> Turnos producidos | D30: =DATALOG!C266 -> 16 | E30: =DATALOG!D266 -> 16 | F30: =DATALOG!E266 -> 24
C31: =DATALOG!B267 -> Produccion promedio por turno | D31: =DATALOG!C267 -> 17451.4 | E31: =DATALOG!D267 -> 8438.8 | F31: =DATALOG!E267 -> 10004.7
C33: =DATALOG!B269 -> Articulo Cafetera
D34: =DATALOG!C270 -> Alemania | E34: =DATALOG!D270 -> Australia | F34: =DATALOG!E270 -> Espana
C35: =DATALOG!B271 -> Promedio del periodo | D35: =DATALOG!C271 -> 9 | E35: =DATALOG!D271 -> 9.4 | F35: =DATALOG!E271 -> 7
C36: =DATALOG!B272 -> Costo minimo para el periodo | D36: =DATALOG!C272 -> 7.1 | E36: =DATALOG!D272 -> 8.7 | F36: =DATALOG!E272 -> 6.7
C37: =DATALOG!B273 -> 0 | D37: =DATALOG!C273 -> 0 | E37: =DATALOG!D273 -> 0 | F37: =DATALOG!E273 -> 0
C38: =DATALOG!B274 -> Total de la produccion (unidades) | D38: =DATALOG!C274 -> 236963 | E38: =DATALOG!D274 -> 164346 | F38: =DATALOG!E274 -> 245822
C39: =DATALOG!B275 -> Turnos producidos | D39: =DATALOG!C275 -> 24 | E39: =DATALOG!D275 -> 19 | F39: =DATALOG!E275 -> 28
C40: =DATALOG!B276 -> Produccion promedio por turno | D40: =DATALOG!C276 -> 9873.5 | E40: =DATALOG!D276 -> 8649.8 | F40: =DATALOG!E276 -> 8779.4
C42: =DATALOG!B278 -> Articulo Licuadora
D43: =DATALOG!C279 -> Alemania | E43: =DATALOG!D279 -> Australia | F43: =DATALOG!E279 -> Espana
C44: =DATALOG!B280 -> Promedio del periodo | D44: =DATALOG!C280 -> 8 | E44: =DATALOG!D280 -> 9 | F44: =DATALOG!E280 -> 7.2
C45: =DATALOG!B281 -> Costo minimo para el periodo | D45: =DATALOG!C281 -> 7.4 | E45: =DATALOG!D281 -> 8.3 | F45: =DATALOG!E281 -> 6.8
C46: =DATALOG!B282 -> 0 | D46: =DATALOG!C282 -> 0 | E46: =DATALOG!D282 -> 0 | F46: =DATALOG!E282 -> 0
C47: =DATALOG!B283 -> Total de la produccion (unidades) | D47: =DATALOG!C283 -> 164636 | E47: =DATALOG!D283 -> 105891 | F47: =DATALOG!E283 -> 174855
C48: =DATALOG!B284 -> Turnos producidos | D48: =DATALOG!C284 -> 18 | E48: =DATALOG!D284 -> 16 | F48: =DATALOG!E284 -> 25
C49: =DATALOG!B285 -> Produccion promedio por turno | D49: =DATALOG!C285 -> 9146.4 | E49: =DATALOG!D285 -> 6618.2 | F49: =DATALOG!E285 -> 6994.2
C51: =DATALOG!B287 -> Articulo FreidoraAire
D52: =DATALOG!C288 -> Alemania | E52: =DATALOG!D288 -> Australia | F52: =DATALOG!E288 -> Espana
C53: =DATALOG!B289 -> Promedio del periodo | D53: =DATALOG!C289 -> 9.3 | E53: =DATALOG!D289 -> 11.5 | F53: =DATALOG!E289 -> 8.6
C54: =DATALOG!B290 -> Costo minimo para el periodo | D54: =DATALOG!C290 -> 8.8 | E54: =DATALOG!D290 -> 11.1 | F54: =DATALOG!E290 -> 8.2
C55: =DATALOG!B291 -> 0 | D55: =DATALOG!C291 -> 0 | E55: =DATALOG!D291 -> 0 | F55: =DATALOG!E291 -> 0
C56: =DATALOG!B292 -> Total de la produccion (unidades) | D56: =DATALOG!C292 -> 48645 | E56: =DATALOG!D292 -> 39853 | F56: =DATALOG!E292 -> 91478
C57: =DATALOG!B293 -> Turnos producidos | D57: =DATALOG!C293 -> 8 | E57: =DATALOG!D293 -> 7 | F57: =DATALOG!E293 -> 14
C58: =DATALOG!B294 -> Produccion promedio por turno | D58: =DATALOG!C294 -> 6080.6 | E58: =DATALOG!D294 -> 5693.3 | F58: =DATALOG!E294 -> 6534.1
C60: =DATALOG!B296 -> Articulo ParrilaElect
D61: =DATALOG!C297 -> Alemania | E61: =DATALOG!D297 -> Australia | F61: =DATALOG!E297 -> Espana
C62: =DATALOG!B298 -> Promedio del periodo | D62: =DATALOG!C298 -> 7.8 | E62: =DATALOG!D298 -> 9.6 | F62: =DATALOG!E298 -> 7.5
C63: =DATALOG!B299 -> Costo minimo para el periodo | D63: =DATALOG!C299 -> 7.4 | E63: =DATALOG!D299 -> 9.5 | F63: =DATALOG!E299 -> 7.1
C64: =DATALOG!B300 -> 0 | D64: =DATALOG!C300 -> 0 | E64: =DATALOG!D300 -> 0 | F64: =DATALOG!E300 -> 0
C65: =DATALOG!B301 -> Total de la produccion (unidades) | D65: =DATALOG!C301 -> 57318 | E65: =DATALOG!D301 -> 42483 | F65: =DATALOG!E301 -> 102594
C66: =DATALOG!B302 -> Turnos producidos | D66: =DATALOG!C302 -> 6 | E66: =DATALOG!D302 -> 7 | F66: =DATALOG!E302 -> 15
C67: =DATALOG!B303 -> Produccion promedio por turno | D67: =DATALOG!C303 -> 9553 | E67: =DATALOG!D303 -> 6069 | F67: =DATALOG!E303 -> 6839.6
C69: =DATALOG!B305 -> 0
D70: =DATALOG!C306 -> 0 | E70: =DATALOG!D306 -> 0 | F70: =DATALOG!E306 -> 0
C71: =DATALOG!B307 -> 0 | D71: =DATALOG!C307 -> 0 | E71: =DATALOG!D307 -> 0 | F71: =DATALOG!E307 -> 0
C72: =DATALOG!B308 -> 0 | D72: =DATALOG!C308 -> 0 | E72: =DATALOG!D308 -> 0 | F72: =DATALOG!E308 -> 0
C73: =DATALOG!B309 -> 0 | D73: =DATALOG!C309 -> 0 | E73: =DATALOG!D309 -> 0 | F73: =DATALOG!E309 -> 0
C74: =DATALOG!B310 -> 0 | D74: =DATALOG!C310 -> 0 | E74: =DATALOG!D310 -> 0 | F74: =DATALOG!E310 -> 0
C75: =DATALOG!B311 -> 0 | D75: =DATALOG!C311 -> 0 | E75: =DATALOG!D311 -> 0 | F75: =DATALOG!E311 -> 0
C76: =DATALOG!B312 -> 0 | D76: =DATALOG!C312 -> 0 | E76: =DATALOG!D312 -> 0 | F76: =DATALOG!E312 -> 0
C78: =DATALOG!B314 -> 0
D79: =DATALOG!C315 -> 0 | E79: =DATALOG!D315 -> 0 | F79: =DATALOG!E315 -> 0
C80: =DATALOG!B316 -> 0 | D80: =DATALOG!C316 -> 0 | E80: =DATALOG!D316 -> 0 | F80: =DATALOG!E316 -> 0
C81: =DATALOG!B317 -> 0 | D81: =DATALOG!C317 -> 0 | E81: =DATALOG!D317 -> 0 | F81: =DATALOG!E317 -> 0
C82: =DATALOG!B318 -> 0 | D82: =DATALOG!C318 -> 0 | E82: =DATALOG!D318 -> 0 | F82: =DATALOG!E318 -> 0
C83: =DATALOG!B319 -> 0 | D83: =DATALOG!C319 -> 0 | E83: =DATALOG!D319 -> 0 | F83: =DATALOG!E319 -> 0
C84: =DATALOG!B320 -> 0 | D84: =DATALOG!C320 -> 0 | E84: =DATALOG!D320 -> 0 | F84: =DATALOG!E320 -> 0
C85: =DATALOG!B321 -> 0 | D85: =DATALOG!C321 -> 0 | E85: =DATALOG!D321 -> 0 | F85: =DATALOG!E321 -> 0

Sheet Informacion Linea 1
C1: INFORMACION DETALLADA PARA | D1: =UPPER(DATALOG!C3) -> CLIMATIZACIO
C3: =UPPER(VLOOKUP(1,DATALOG!A1:H320,2,FALSE)) -> INFORMACION DETALLADA DE ALEMANIA PARA CLIMATIZACIO HASTA EL PERIODO 7.
C4: =VLOOKUP(1,DATALOG!A2:H321,2,FALSE) -> Pais | D4: =DATALOG!C2 -> Alemania | E4: =DATALOG!D2 -> Alemania | F4: =DATALOG!E2 -> Alemania | G4: =DATALOG!F2 -> Alemania | H4: =DATALOG!G2 -> Alemania | I4: =DATALOG!H2 -> Alemania | J4: =DATALOG!I2 -> Alemania | K4: =DATALOG!J2 -> 0 | L4: =DATALOG!K2 -> 0
C5: =VLOOKUP(1,DATALOG!A3:H322,2,FALSE) -> Lineas de Productos | D5: =DATALOG!C3 -> Climatizacio | E5: =DATALOG!D3 -> Climatizacio | F5: =DATALOG!E3 -> Climatizacio | G5: =DATALOG!F3 -> Climatizacio | H5: =DATALOG!G3 -> Climatizacio | I5: =DATALOG!H3 -> Climatizacio | J5: =DATALOG!I3 -> Climatizacio | K5: =DATALOG!J3 -> 0 | L5: =DATALOG!K3 -> 0
C6: =VLOOKUP(1,DATALOG!A4:H323,2,FALSE) -> Articulo | D6: =DATALOG!C4 -> EstufaGas | E6: =DATALOG!D4 -> EstufaElectr | F6: =DATALOG!E4 -> VentPedestal | G6: =DATALOG!F4 -> Vent_Torre | H6: =DATALOG!G4 -> Purif_Aire | I6: =DATALOG!H4 -> Deshumidific | J6: =DATALOG!I4 -> Ionizador | K6: =DATALOG!J4 -> 0 | L6: =DATALOG!K4 -> 0
C7: =VLOOKUP(1,DATALOG!A5:H324,2,FALSE) -> Precio promedio historico unidades vendidas a consumidores | D7: =DATALOG!C5 -> 96 | E7: =DATALOG!D5 -> 109.17 | F7: =DATALOG!E5 -> 33.33 | G7: =DATALOG!F5 -> 47.5 | H7: =DATALOG!G5 -> 74.17 | I7: =DATALOG!H5 -> 122 | J7: =DATALOG!I5 -> 80 | K7: =DATALOG!J5 -> 0 | L7: =DATALOG!K5 -> 0
C8: =VLOOKUP(1,DATALOG!A6:H325,2,FALSE) -> Variacion de precio respecto periodo anterior (%) | D8: =DATALOG!C6 -> 0.062 | E8: =DATALOG!D6 -> 0.018 | F8: =DATALOG!E6 -> 0.029 | G8: =DATALOG!F6 -> 0.104 | H8: =DATALOG!G6 -> 0.039 | I8: =DATALOG!H6 -> 0 | J8: =DATALOG!I6 -> 0 | K8: =DATALOG!J6 -> 0 | L8: =DATALOG!K6 -> 0
C9: =VLOOKUP(1,DATALOG!A7:H326,2,FALSE) -> Precio que consumidores estan dispuestos a pagar | D9: =DATALOG!C7 -> 104 | E9: =DATALOG!D7 -> 116 | F9: =DATALOG!E7 -> 34 | G9: =DATALOG!F7 -> 51 | H9: =DATALOG!G7 -> 80 | I9: =DATALOG!H7 -> 120 | J9: =DATALOG!I7 -> 80 | K9: =DATALOG!J7 -> 0 | L9: =DATALOG!K7 -> 0
C10: =VLOOKUP(1,DATALOG!A8:H327,2,FALSE) -> Precio promedio ofrecido a consumidores en periodo 7 | D10: =DATALOG!C8 -> 103 | E10: =DATALOG!D8 -> 111 | F10: =DATALOG!E8 -> 35 | G10: =DATALOG!F8 -> 53 | H10: =DATALOG!G8 -> 79 | I10: =DATALOG!H8 -> 122 | J10: =DATALOG!I8 -> 80 | K10: =DATALOG!J8 -> 0 | L10: =DATALOG!K8 -> 0
C11: =VLOOKUP(1,DATALOG!A9:H328,2,FALSE) -> Ventas a consumidores total | D11: =DATALOG!C9 -> 99459 | E11: =DATALOG!D9 -> 109066 | F11: =DATALOG!E9 -> 69566 | G11: =DATALOG!F9 -> 65213 | H11: =DATALOG!G9 -> 100754 | I11: =DATALOG!H9 -> 46920 | J11: =DATALOG!I9 -> 2000 | K11: =DATALOG!J9 -> 0 | L11: =DATALOG!K9 -> 0
C12: =VLOOKUP(1,DATALOG!A10:H329,2,FALSE) -> Empresas vendiendo a consumidores | D12: =DATALOG!C10 -> 23 | E12: =DATALOG!D10 -> 24 | F12: =DATALOG!E10 -> 23 | G12: =DATALOG!F10 -> 19 | H12: =DATALOG!G10 -> 28 | I12: =DATALOG!H10 -> 13 | J12: =DATALOG!I10 -> 1 | K12: =DATALOG!J10 -> 0 | L12: =DATALOG!K10 -> 0
C13: =VLOOKUP(1,DATALOG!A11:H330,2,FALSE) -> Empresas presentes en mcdo. consumidores con linea de productos | D13: =DATALOG!C11 -> 38 | E13: =DATALOG!D11 -> 38 | F13: =DATALOG!E11 -> 38 | G13: =DATALOG!F11 -> 38 | H13: =DATALOG!G11 -> 38 | I13: =DATALOG!H11 -> 38 | J13: =DATALOG!I11 -> 38 | K13: =DATALOG!J11 -> 0 | L13: =DATALOG!K11 -> 0
C14: =VLOOKUP(1,DATALOG!A12:H331,2,FALSE) -> Inventario final | D14: =DATALOG!C12 -> 289245 | E14: =DATALOG!D12 -> 281434 | F14: =DATALOG!E12 -> 294198 | G14: =DATALOG!F12 -> 370214 | H14: =DATALOG!G12 -> 433254 | I14: =DATALOG!H12 -> 117180 | J14: =DATALOG!I12 -> 79983 | K14: =DATALOG!J12 -> 0 | L14: =DATALOG!K12 -> 0
C15: =VLOOKUP(1,DATALOG!A13:H332,2,FALSE) -> Cantidad producida este periodo | D15: =DATALOG!C13 -> 131308 | E15: =DATALOG!D13 -> 128875 | F15: =DATALOG!E13 -> 200481 | G15: =DATALOG!F13 -> 253714 | H15: =DATALOG!G13 -> 274318 | I15: =DATALOG!H13 -> 19500 | J15: =DATALOG!I13 -> 43959 | K15: =DATALOG!J13 -> 0 | L15: =DATALOG!K13 -> 0
... C19: =VLOOKUP(1,DATALOG!A17:H336,2,FALSE) -> Gasto promedio en Responsabilidad Social | D19: =DATALOG!C17 -> 23154 | E19: =DATALOG!D17 -> 26882 | F19: =DATALOG!E17 -> 21586 | G19: =DATALOG!F17 -> 23215 | H19: =DATALOG!G17 -> 22546 | I19: =DATALOG!H17 -> 27433 | J19: =DATALOG!I17 -> 781 | K19: =DATALOG!J17 -> 0 | L19: =DATALOG!K17 -> 0
C21: =UPPER(DATALOG!B18) -> INFORMACION DETALLADA DE AUSTRALIA PARA CLIMATIZACIO HASTA EL PERIODO 7.
C22: =DATALOG!B19 -> Pais | D22: =DATALOG!C19 -> Australia | E22: =DATALOG!D19 -> Australia | F22: =DATALOG!E19 -> Australia | G22: =DATALOG!F19 -> Australia | H22: =DATALOG!G19 -> Australia | I22: =DATALOG!H19 -> Australia | J22: =DATALOG!I19 -> Australia | ... L22: =DATALOG!K19 -> 0
C23: =DATALOG!B20 -> Lineas de Productos | D23: =DATALOG!C20 -> Climatizacio | E23: =DATALOG!D20 -> Climatizacio | F23: =DATALOG!E20 -> Climatizacio | G23: =DATALOG!F20 -> Climatizacio | H23: =DATALOG!G20 -> Climatizacio | I23: =DATALOG!H20 -> Climatizacio | J23: =DATALOG!I20 -> Climatizacio | ... L23: =DATALOG!K20 -> 0
C24: =DATALOG!B21 -> Articulo | D24: =DATALOG!C21 -> EstufaGas | E24: =DATALOG!D21 -> EstufaElectr | F24: =DATALOG!E21 -> VentPedestal | G24: =DATALOG!F21 -> Vent_Torre | H24: =DATALOG!G21 -> Purif_Aire | I24: =DATALOG!H21 -> Deshumidific | J24: =DATALOG!I21 -> Ionizador | ... L24: =DATALOG!K21 -> 0
C25: =DATALOG!B22 -> Precio promedio historico unidades vendidas a consumidores | D25: =DATALOG!C22 -> 96.5 | E25: =DATALOG!D22 -> 128.17 | F25: =DATALOG!E22 -> 41.33 | G25: =DATALOG!F22 -> 58.33 | H25: =DATALOG!G22 -> 81.83 | I25: =DATALOG!H22 -> 122 | J25: =DATALOG!I22 -> 80 | ... L25: =DATALOG!K22 -> 0
C26: =DATALOG!B23 -> Variacion de precio respecto periodo anterior (%) | D26: =DATALOG!C23 -> 0.04 | E26: =DATALOG!D23 -> -0.023 | F26: =DATALOG!E23 -> 0.048 | G26: =DATALOG!F23 -> 0.051 | H26: =DATALOG!G23 -> 0.012 | I26: =DATALOG!H23 -> 0 | J26: =DATALOG!I23 -> 0 | ... L26: =DATALOG!K23 -> 0
C27: =DATALOG!B24 -> Precio que consumidores estan dispuestos a pagar | D27: =DATALOG!C24 -> 103 | E27: =DATALOG!D24 -> 134 | F27: =DATALOG!E24 -> 44 | G27: =DATALOG!F24 -> 62 | H27: =DATALOG!G24 -> 88 | I27: =DATALOG!H24 -> 115 | J27: =DATALOG!I24 -> 80 | ... L27: =DATALOG!K24 -> 0
C28: =DATALOG!B25 -> Precio promedio ofrecido a consumidores en periodo 7 | D28: =DATALOG!C25 -> 104 | E28: =DATALOG!D25 -> 129 | F28: =DATALOG!E25 -> 44 | G28: =DATALOG!F25 -> 62 | H28: =DATALOG!G25 -> 86 | I28: =DATALOG!H25 -> 122 | J28: =DATALOG!I25 -> 80 | ... L28: =DATALOG!K25 -> 0
C29: =DATALOG!B26 -> Ventas a consumidores total | D29: =DATALOG!C26 -> 44719 | E29: =DATALOG!D26 -> 34434 | F29: =DATALOG!E26 -> 165788 | G29: =DATALOG!F26 -> 143347 | H29: =DATALOG!G26 -> 152006 | I29: =DATALOG!H26 -> 38328 | J29: =DATALOG!I26 -> 2784 | ... L29: =DATALOG!K26 -> 0
C30: =DATALOG!B27 -> Empresas vendiendo a consumidores | D30: =DATALOG!C27 -> 14 | E30: =DATALOG!D27 -> 12 | F30: =DATALOG!E27 -> 30 | G30: =DATALOG!F27 -> 25 | H30: =DATALOG!G27 -> 27 | I30: =DATALOG!H27 -> 7 | J30: =DATALOG!I27 -> 1 | ... L30: =DATALOG!K27 -> 0
C31: =DATALOG!B28 -> Empresas presentes en mcdo. consumidores con linea de productos | D31: =DATALOG!C28 -> 35 | E31: =DATALOG!D28 -> 35 | F31: =DATALOG!E28 -> 35 | G31: =DATALOG!F28 -> 35 | H31: =DATALOG!G28 -> 35 | I31: =DATALOG!H28 -> 35 | J31: =DATALOG!I28 -> 35 | ... L31: =DATALOG!K28 -> 0
C32: =DATALOG!B29 -> Inventario final | D32: =DATALOG!C29 -> 177790 | E32: =DATALOG!D29 -> 196372 | F32: =DATALOG!E29 -> 396410 | G32: =DATALOG!F29 -> 491533 | H32: =DATALOG!G29 -> 382583 | I32: =DATALOG!H29 -> 133033 | J32: =DATALOG!I29 -> 107490 | ... L32: =DATALOG!K29 -> 0
C33: =DATALOG!B30 -> Cantidad producida este periodo | D33: =DATALOG!C30 -> 127607 | E33: =DATALOG!D30 -> 132590 | F33: =DATALOG!E30 -> 99175 | G33: =DATALOG!F30 -> 187502 | H33: =DATALOG!G30 -> 148144 | I33: =DATALOG!H30 -> 37947 | J33: =DATALOG!I30 -> 51525 | ... L33: =DATALOG!K30 -> 0
... C37: =DATALOG!B34 -> Gasto promedio en Responsabilidad Social | D37: =DATALOG!C34 -> 32824 | E37: =DATALOG!D34 -> 34460 | F37: =DATALOG!E34 -> 28437 | G37: =DATALOG!F34 -> 28483 | H37: =DATALOG!G34 -> 30254 | I37: =DATALOG!H34 -> 24799 | J37: =DATALOG!I34 -> 0 | ... L37: =DATALOG!K34 -> 0
C39: =UPPER(DATALOG!B35) -> INFORMACION DETALLADA DE ESPANA PARA CLIMATIZACIO HASTA EL PERIODO 7.
C40: =DATALOG!B36 -> Pais | D40: =DATALOG!C36 -> Espana | E40: =DATALOG!D36 -> Espana | F40: =DATALOG!E36 -> Espana | G40: =DATALOG!F36 -> Espana | H40: =DATALOG!G36 -> Espana | I40: =DATALOG!H36 -> Espana | J40: =DATALOG!I36 -> Espana | ... L40: =DATALOG!K36 -> 0
C41: =DATALOG!B37 -> Lineas de Productos | D41: =DATALOG!C37 -> Climatizacio | E41: =DATALOG!D37 -> Climatizacio | F41: =DATALOG!E37 -> Climatizacio | G41: =DATALOG!F37 -> Climatizacio | H41: =DATALOG!G37 -> Climatizacio | I41: =DATALOG!H37 -> Climatizacio | J41: =DATALOG!I37 -> Climatizacio | ... L41: =DATALOG!K37 -> 0
C42: =DATALOG!B38 -> Articulo | D42: =DATALOG!C38 -> EstufaGas | E42: =DATALOG!D38 -> EstufaElectr | F42: =DATALOG!E38 -> VentPedestal | G42: =DATALOG!F38 -> Vent_Torre | H42: =DATALOG!G38 -> Purif_Aire | I42: =DATALOG!H38 -> Deshumidific | J42: =DATALOG!I38 -> Ionizador | ... L42: =DATALOG!K38 -> 0
C43: =DATALOG!B39 -> Precio promedio historico unidades vendidas a consumidores | D43: =DATALOG!C39 -> 91.5 | E43: =DATALOG!D39 -> 113.5 | F43: =DATALOG!E39 -> 38.67 | G43: =DATALOG!F39 -> 53.33 | H43: =DATALOG!G39 -> 81.67 | I43: =DATALOG!H39 -> 117 | J43: =DATALOG!I39 -> 82 | ... L43: =DATALOG!K39 -> 0
C44: =DATALOG!B40 -> Variacion de precio respecto periodo anterior (%) | D44: =DATALOG!C40 -> 0.021 | E44: =DATALOG!D40 -> 0.017 | F44: =DATALOG!E40 -> 0.026 | G44: =DATALOG!F40 -> 0 | H44: =DATALOG!G40 -> 0.048 | I44: =DATALOG!H40 -> 0 | J44: =DATALOG!I40 -> 0 | ... L44: =DATALOG!K40 -> 0
C45: =DATALOG!B41 -> Precio que consumidores estan dispuestos a pagar | D45: =DATALOG!C41 -> 97 | E45: =DATALOG!D41 -> 121 | F45: =DATALOG!E41 -> 40 | G45: =DATALOG!F41 -> 56 | H45: =DATALOG!G41 -> 86 | I45: =DATALOG!H41 -> 120 | J45: =DATALOG!I41 -> 85 | ... L45: =DATALOG!K41 -> 0
C46: =DATALOG!B42 -> Precio promedio ofrecido a consumidores en periodo 7 | D46: =DATALOG!C42 -> 97 | E46: =DATALOG!D42 -> 120 | F46: =DATALOG!E42 -> 40 | G46: =DATALOG!F42 -> 55 | H46: =DATALOG!G42 -> 87 | I46: =DATALOG!H42 -> 117 | J46: =DATALOG!I42 -> 82 | ... L46: =DATALOG!K42 -> 0
C47: =DATALOG!B43 -> Ventas a consumidores total | D47: =DATALOG!C43 -> 82593 | E47: =DATALOG!D43 -> 81633 | F47: =DATALOG!E43 -> 121401 | G47: =DATALOG!F43 -> 84652 | H47: =DATALOG!G43 -> 109884 | I47: =DATALOG!H43 -> 65016 | J47: =DATALOG!I43 -> 9575 | ... L47: =DATALOG!K43 -> 0
C48: =DATALOG!B44 -> Empresas vendiendo a consumidores | D48: =DATALOG!C44 -> 21 | E48: =DATALOG!D44 -> 21 | F48: =DATALOG!E44 -> 22 | G48: =DATALOG!F44 -> 23 | H48: =DATALOG!G44 -> 29 | I48: =DATALOG!H44 -> 15 | J48: =DATALOG!I44 -> 3 | ... L48: =DATALOG!K44 -> 0
C49: =DATALOG!B45 -> Empresas presentes en mcdo. consumidores con linea de productos | D49: =DATALOG!C45 -> 35 | E49: =DATALOG!D45 -> 35 | F49: =DATALOG!E45 -> 35 | G49: =DATALOG!F45 -> 35 | H49: =DATALOG!G45 -> 35 | I49: =DATALOG!H45 -> 35 | J49: =DATALOG!I45 -> 35 | ... L49: =DATALOG!K45 -> 0
C50: =DATALOG!B46 -> Inventario final | D50: =DATALOG!C46 -> 267438 | E50: =DATALOG!D46 -> 290286 | F50: =DATALOG!E46 -> 363426 | G50: =DATALOG!F46 -> 285324 | H50: =DATALOG!G46 -> 433912 | I50: =DATALOG!H46 -> 121533 | J50: =DATALOG!I46 -> 85826 | ... L50: =DATALOG!K46 -> 0
C51: =DATALOG!B47 -> Cantidad producida este periodo | D51: =DATALOG!C47 -> 116749 | E51: =DATALOG!D47 -> 115436 | F51: =DATALOG!E47 -> 255734 | G51: =DATALOG!F47 -> 208288 | H51: =DATALOG!G47 -> 241266 | I51: =DATALOG!H47 -> 54177 | J51: =DATALOG!I47 -> 52467 | ... L51: =DATALOG!K47 -> 0
... C55: =DATALOG!B51 -> Gasto promedio en Responsabilidad Social | D55: =DATALOG!C51 -> 31027 | E55: =DATALOG!D51 -> 32084 | F55: =DATALOG!E51 -> 36647 | G55: =DATALOG!F51 -> 35882 | H55: =DATALOG!G51 -> 28960 | I55: =DATALOG!H51 -> 37773 | J55: =DATALOG!I51 -> 11667 | ... L55: =DATALOG!K51 -> 0
C58: =UPPER(DATALOG!B121) -> GASTOS HISTORICOS PROMEDIO CONSIDERANDO
D60: =DATALOG!C122 -> Alemania | E60: =DATALOG!D122 -> Australia | F60: =DATALOG!E122 -> Espana
C61: =DATALOG!B123 -> Mantencion de fabrica de Climatizacio | D61: =DATALOG!C123 -> 333780.3 | E61: =DATALOG!D123 -> 323381.1 | F61: =DATALOG!E123 -> 245009.7
C62: =DATALOG!B124 -> Mantencion de fabrica de Electrodomes | D62: =DATALOG!C124 -> 373919.7 | E62: =DATALOG!D124 -> 367900.8 | F62: =DATALOG!E124 -> 284640.3
C63: =DATALOG!B125 -> Publicidad para linea Climatizacio | D63: =DATALOG!C125 -> 100657.8 | E63: =DATALOG!D125 -> 113517.5 | F63: =DATALOG!E125 -> 106748.2
C64: =DATALOG!B126 -> Publicidad para linea Electrodomes | D64: =DATALOG!C126 -> 95255.5 | E64: =DATALOG!D126 -> 109668.6 | F64: =DATALOG!E126 -> 116667.8
C65: =DATALOG!B127 -> Comercializacion para linea Climatizacio | D65: =DATALOG!C127 -> 33807.8 | E65: =DATALOG!D127 -> 28645.6 | F65: =DATALOG!E127 -> 32175.8
C66: =DATALOG!B128 -> Comercializacion para linea Electrodomes | D66: =DATALOG!C128 -> 58330.2 | E66: =DATALOG!D128 -> 37893.5 | F66: =DATALOG!E128 -> 47362

Sheet Informacion Linea 2
C1: INFORMACION DETALLADA PARA | D1: =UPPER(DATALOG!C54) -> ELECTRODOMES
C3: =UPPER(DATALOG!B52) -> INFORMACION DETALLADA DE ALEMANIA PARA ELECTRODOMES HASTA EL PERIODO 7.
C4: =DATALOG!B53 -> Pais | D4: =DATALOG!C53 -> Alemania | E4: =DATALOG!D53 -> Alemania | F4: =DATALOG!E53 -> Alemania | G4: =DATALOG!F53 -> Alemania | H4: =DATALOG!G53 -> Alemania | I4: =DATALOG!H53 -> Alemania | J4: =DATALOG!I53 -> Alemania | ... L4: =DATALOG!K53 -> 0
C5: =DATALOG!B54 -> Lineas de Productos | D5: =DATALOG!C54 -> Electrodomes | E5: =DATALOG!D54 -> Electrodomes | F5: =DATALOG!E54 -> Electrodomes | G5: =DATALOG!F54 -> Electrodomes | H5: =DATALOG!G54 -> Electrodomes | I5: =DATALOG!H54 -> Electrodomes | J5: =DATALOG!I54 -> Electrodomes | ... L5: =DATALOG!K54 -> 0
C6: =DATALOG!B55 -> Articulo | D6: =DATALOG!C55 -> Hervidor | E6: =DATALOG!D55 -> Tostador | F6: =DATALOG!E55 -> Batidora | G6: =DATALOG!F55 -> Cafetera | H6: =DATALOG!G55 -> Licuadora | I6: =DATALOG!H55 -> FreidoraAire | J6: =DATALOG!I55 -> ParrilaElect | ... L6: =DATALOG!K55 -> 0
C7: =DATALOG!B56 -> Precio promedio historico unidades vendidas a consumidores | D7: =DATALOG!C56 -> 30.33 | E7: =DATALOG!D56 -> 26.33 | F7: =DATALOG!E56 -> 26.83 | G7: =DATALOG!F56 -> 35.83 | H7: =DATALOG!G56 -> 38 | I7: =DATALOG!H56 -> 65 | J7: =DATALOG!I56 -> 56 | ... L7: =DATALOG!K56 -> 0
C8: =DATALOG!B57 -> Variacion de precio respecto periodo anterior (%) | D8: =DATALOG!C57 -> 0.032 | E8: =DATALOG!D57 -> 0.037 | F8: =DATALOG!E57 -> 0 | G8: =DATALOG!F57 -> 0.027 | H8: =DATALOG!G57 -> 0.051 | I8: =DATALOG!H57 -> 0 | J8: =DATALOG!I57 -> 0 | ... L8: =DATALOG!K57 -> 0
C9: =DATALOG!B58 -> Precio que consumidores estan dispuestos a pagar | D9: =DATALOG!C58 -> 32 | E9: =DATALOG!D58 -> 29 | F9: =DATALOG!E58 -> 28 | G9: =DATALOG!F58 -> 39 | H9: =DATALOG!G58 -> 40 | I9: =DATALOG!H58 -> 65 | J9: =DATALOG!I58 -> 55 | ... L9: =DATALOG!K58 -> 0
C10: =DATALOG!B59 -> Precio promedio ofrecido a consumidores en periodo 7 | D10: =DATALOG!C59 -> 32 | E10: =DATALOG!D59 -> 28 | F10: =DATALOG!E59 -> 28 | G10: =DATALOG!F59 -> 38 | H10: =DATALOG!G59 -> 41 | I10: =DATALOG!H59 -> 65 | J10: =DATALOG!I59 -> 56 | ... L10: =DATALOG!K59 -> 0
C11: =DATALOG!B60 -> Ventas a consumidores total | D11: =DATALOG!C60 -> 141222 | E11: =DATALOG!D60 -> 108293 | F11: =DATALOG!E60 -> 121688 | G11: =DATALOG!F60 -> 131051 | H11: =DATALOG!G60 -> 105411 | I11: =DATALOG!H60 -> 65394 | J11: =DATALOG!I60 -> 2573 | ... L11: =DATALOG!K60 -> 0
C12: =DATALOG!B61 -> Empresas vendiendo a consumidores | D12: =DATALOG!C61 -> 25 | E12: =DATALOG!D61 -> 18 | F12: =DATALOG!E61 -> 20 | G12: =DATALOG!F61 -> 24 | H12: =DATALOG!G61 -> 20 | I12: =DATALOG!H61 -> 12 | J12: =DATALOG!I61 -> 1 | ... L12: =DATALOG!K61 -> 0
C13: =DATALOG!B62 -> Empresas presentes en mcdo. consumidores con linea de productos | D13: =DATALOG!C62 -> 29 | E13: =DATALOG!D62 -> 29 | F13: =DATALOG!E62 -> 29 | G13: =DATALOG!F62 -> 29 | H13: =DATALOG!G62 -> 29 | I13: =DATALOG!H62 -> 29 | J13: =DATALOG!I62 -> 29 | ... L13: =DATALOG!K62 -> 0
C14: =DATALOG!B63 -> Inventario final | D14: =DATALOG!C63 -> 427557 | E14: =DATALOG!D63 -> 414306 | F14: =DATALOG!E63 -> 480691 | G14: =DATALOG!F63 -> 422466 | H14: =DATALOG!G63 -> 295881 | I14: =DATALOG!H63 -> 148535 | J14: =DATALOG!I63 -> 94425 | ... L14: =DATALOG!K63 -> 0
C15: =DATALOG!B64 -> Cantidad producida este periodo | D15: =DATALOG!C64 -> 207207 | E15: =DATALOG!D64 -> 227421 | F15: =DATALOG!E64 -> 279222 | G15: =DATALOG!F64 -> 236963 | H15: =DATALOG!G64 -> 164636 | I15: =DATALOG!H64 -> 48645 | J15: =DATALOG!I64 -> 57318 | ... L15: =DATALOG!K64 -> 0
... C19: =DATALOG!B68 -> Gasto promedio en Responsabilidad Social | D19: =DATALOG!C68 -> 25128 | E19: =DATALOG!D68 -> 27538 | F19: =DATALOG!E68 -> 25798 | G19: =DATALOG!F68 -> 25953 | H19: =DATALOG!G68 -> 26173 | I19: =DATALOG!H68 -> 26021 | J19: =DATALOG!I68 -> 0 | ... L19: =DATALOG!K68 -> 0
C21: =UPPER(DATALOG!B69) -> INFORMACION DETALLADA DE AUSTRALIA PARA ELECTRODOMES HASTA EL PERIODO 7.
C22: =DATALOG!B70 -> Pais | D22: =DATALOG!C70 -> Australia | E22: =DATALOG!D70 -> Australia | F22: =DATALOG!E70 -> Australia | G22: =DATALOG!F70 -> Australia | H22: =DATALOG!G70 -> Australia | I22: =DATALOG!H70 -> Australia | J22: =DATALOG!I70 -> Australia | ... L22: =DATALOG!K70 -> 0
C23: =DATALOG!B71 -> Lineas de Productos | D23: =DATALOG!C71 -> Electrodomes | E23: =DATALOG!D71 -> Electrodomes | F23: =DATALOG!E71 -> Electrodomes | G23: =DATALOG!F71 -> Electrodomes | H23: =DATALOG!G71 -> Electrodomes | I23: =DATALOG!H71 -> Electrodomes | J23: =DATALOG!I71 -> Electrodomes | ... L23: =DATALOG!K71 -> 0
C24: =DATALOG!B72 -> Articulo | D24: =DATALOG!C72 -> Hervidor | E24: =DATALOG!D72 -> Tostador | F24: =DATALOG!E72 -> Batidora | G24: =DATALOG!F72 -> Cafetera | H24: =DATALOG!G72 -> Licuadora | I24: =DATALOG!H72 -> FreidoraAire | J24: =DATALOG!I72 -> ParrilaElect | ... L24: =DATALOG!K72 -> 0
C25: =DATALOG!B73 -> Precio promedio historico unidades vendidas a consumidores | D25: =DATALOG!C73 -> 34.67 | E25: =DATALOG!D73 -> 33.33 | F25: =DATALOG!E73 -> 27 | G25: =DATALOG!F73 -> 44.83 | H25: =DATALOG!G73 -> 47.5 | I25: =DATALOG!H73 -> 65 | J25: =DATALOG!I73 -> 50 | ... L25: =DATALOG!K73 -> 0
C26: =DATALOG!B74 -> Variacion de precio respecto periodo anterior (%) | D26: =DATALOG!C74 -> 0.029 | E26: =DATALOG!D74 -> 0.029 | F26: =DATALOG!E74 -> 0.036 | G26: =DATALOG!F74 -> 0 | H26: =DATALOG!G74 -> 0.02 | I26: =DATALOG!H74 -> 0 | J26: =DATALOG!I74 -> 0 | ... L26: =DATALOG!K74 -> 0
C27: =DATALOG!B75 -> Precio que consumidores estan dispuestos a pagar | D27: =DATALOG!C75 -> 37 | E27: =DATALOG!D75 -> 35 | F27: =DATALOG!E75 -> 28 | G27: =DATALOG!F75 -> 47 | H27: =DATALOG!G75 -> 50 | I27: =DATALOG!H75 -> 65 | J27: =DATALOG!I75 -> 0 | ... L27: =DATALOG!K75 -> 0
C28: =DATALOG!B76 -> Precio promedio ofrecido a consumidores en periodo 7 | D28: =DATALOG!C76 -> 36 | E28: =DATALOG!D76 -> 35 | F28: =DATALOG!E76 -> 29 | G28: =DATALOG!F76 -> 45 | H28: =DATALOG!G76 -> 50 | I28: =DATALOG!H76 -> 65 | J28: =DATALOG!I76 -> 0 | ... L28: =DATALOG!K76 -> 0
C29: =DATALOG!B77 -> Ventas a consumidores total | D29: =DATALOG!C77 -> 160562 | E29: =DATALOG!D77 -> 107969 | F29: =DATALOG!E77 -> 160219 | G29: =DATALOG!F77 -> 165104 | H29: =DATALOG!G77 -> 109402 | I29: =DATALOG!H77 -> 68100 | J29: =DATALOG!I77 -> 0 | ... L29: =DATALOG!K77 -> 0
C30: =DATALOG!B78 -> Empresas vendiendo a consumidores | D30: =DATALOG!C78 -> 30 | E30: =DATALOG!D78 -> 25 | F30: =DATALOG!E78 -> 26 | G30: =DATALOG!F78 -> 32 | H30: =DATALOG!G78 -> 30 | I30: =DATALOG!H78 -> 11 | J30: =DATALOG!I78 -> 0 | ... L30: =DATALOG!K78 -> 0
C31: =DATALOG!B79 -> Empresas presentes en mcdo. consumidores con linea de productos | D31: =DATALOG!C79 -> 39 | E31: =DATALOG!D79 -> 39 | F31: =DATALOG!E79 -> 39 | G31: =DATALOG!F79 -> 39 | H31: =DATALOG!G79 -> 39 | I31: =DATALOG!H79 -> 39 | J31: =DATALOG!I79 -> 0 | ... L31: =DATALOG!K79 -> 0
C32: =DATALOG!B80 -> Inventario final | D32: =DATALOG!C80 -> 455324 | E32: =DATALOG!D80 -> 398832 | F32: =DATALOG!E80 -> 339874 | G32: =DATALOG!F80 -> 421229 | H32: =DATALOG!G80 -> 314030 | I32: =DATALOG!H80 -> 168062 | J32: =DATALOG!I80 -> 102959 | ... L32: =DATALOG!K80 -> 0
C33: =DATALOG!B81 -> Cantidad producida este periodo | D33: =DATALOG!C81 -> 209172 | E33: =DATALOG!D81 -> 195682 | F33: =DATALOG!E81 -> 135020 | G33: =DATALOG!F81 -> 164346 | H33: =DATALOG!G81 -> 105891 | I33: =DATALOG!H81 -> 39853 | J33: =DATALOG!I81 -> 42483 | ... L33: =DATALOG!K81 -> 0
... C37: =DATALOG!B85 -> Gasto promedio en Responsabilidad Social | D37: =DATALOG!C85 -> 27110 | E37: =DATALOG!D85 -> 27385 | F37: =DATALOG!E85 -> 27266 | G37: =DATALOG!F85 -> 26177 | H37: =DATALOG!G85 -> 27516 | I37: =DATALOG!H85 -> 25412 | J37: =DATALOG!I85 -> 0 | ... L37: =DATALOG!K85 -> 0
C39: =UPPER(DATALOG!B86) -> INFORMACION DETALLADA DE ESPANA PARA ELECTRODOMES HASTA EL PERIODO 7.
C40: =DATALOG!B87 -> Pais | D40: =DATALOG!C87 -> Espana | E40: =DATALOG!D87 -> Espana | F40: =DATALOG!E87 -> Espana | G40: =DATALOG!F87 -> Espana | H40: =DATALOG!G87 -> Espana | I40: =DATALOG!H87 -> Espana | J40: =DATALOG!I87 -> Espana | ... L40: =DATALOG!K87 -> 0
C41: =DATALOG!B88 -> Lineas de Productos | D41: =DATALOG!C88 -> Electrodomes | E41: =DATALOG!D88 -> Electrodomes | F41: =DATALOG!E88 -> Electrodomes | G41: =DATALOG!F88 -> Electrodomes | H41: =DATALOG!G88 -> Electrodomes | I41: =DATALOG!H88 -> Electrodomes | J41: =DATALOG!I88 -> Electrodomes | ... L41: =DATALOG!K88 -> 0
C42: =DATALOG!B89 -> Articulo | D42: =DATALOG!C89 -> Hervidor | E42: =DATALOG!D89 -> Tostador | F42: =DATALOG!E89 -> Batidora | G42: =DATALOG!F89 -> Cafetera | H42: =DATALOG!G89 -> Licuadora | I42: =DATALOG!H89 -> FreidoraAire | J42: =DATALOG!I89 -> ParrilaElect | ... L42: =DATALOG!K89 -> 0
C43: =DATALOG!B90 -> Precio promedio historico unidades vendidas a consumidores | D43: =DATALOG!C90 -> 27.5 | E43: =DATALOG!D90 -> 26.67 | F43: =DATALOG!E90 -> 23.83 | G43: =DATALOG!F90 -> 30.67 | H43: =DATALOG!G90 -> 31.5 | I43: =DATALOG!H90 -> 61 | J43: =DATALOG!I90 -> 53 | ... L43: =DATALOG!K90 -> 0
C44: =DATALOG!B91 -> Variacion de precio respecto periodo anterior (%) | D44: =DATALOG!C91 -> 0.036 | E44: =DATALOG!D91 -> 0.074 | F44: =DATALOG!E91 -> 0.04 | G44: =DATALOG!F91 -> 0 | H44: =DATALOG!G91 -> 0.061 | I44: =DATALOG!H91 -> 0 | J44: =DATALOG!I91 -> 0 | ... L44: =DATALOG!K91 -> 0
C45: =DATALOG!B92 -> Precio que consumidores estan dispuestos a pagar | D45: =DATALOG!C92 -> 29 | E45: =DATALOG!D92 -> 28 | F45: =DATALOG!E92 -> 25 | G45: =DATALOG!F92 -> 32 | H45: =DATALOG!G92 -> 32 | I45: =DATALOG!H92 -> 60 | J45: =DATALOG!I92 -> 55 | ... L45: =DATALOG!K92 -> 0
C46: =DATALOG!B93 -> Precio promedio ofrecido a consumidores en periodo 7 | D46: =DATALOG!C93 -> 29 | E46: =DATALOG!D93 -> 29 | F46: =DATALOG!E93 -> 26 | G46: =DATALOG!F93 -> 33 | H46: =DATALOG!G93 -> 35 | I46: =DATALOG!H93 -> 61 | J46: =DATALOG!I93 -> 53 | ... L46: =DATALOG!K93 -> 0
C47: =DATALOG!B94 -> Ventas a consumidores total | D47: =DATALOG!C94 -> 137025 | E47: =DATALOG!D94 -> 91544 | F47: =DATALOG!E94 -> 171943 | G47: =DATALOG!F94 -> 117641 | H47: =DATALOG!G94 -> 94820 | I47: =DATALOG!H94 -> 107545 | J47: =DATALOG!I94 -> 9051 | ... L47: =DATALOG!K94 -> 0
C48: =DATALOG!B95 -> Empresas vendiendo a consumidores | D48: =DATALOG!C95 -> 24 | E48: =DATALOG!D95 -> 19 | F48: =DATALOG!E95 -> 29 | G48: =DATALOG!F95 -> 25 | H48: =DATALOG!G95 -> 22 | I48: =DATALOG!H95 -> 20 | J48: =DATALOG!I95 -> 4 | ... L48: =DATALOG!K95 -> 0
C49: =DATALOG!B96 -> Empresas presentes en mcdo. consumidores con linea de productos | D49: =DATALOG!C96 -> 35 | E49: =DATALOG!D96 -> 35 | F49: =DATALOG!E96 -> 35 | G49: =DATALOG!F96 -> 35 | H49: =DATALOG!G96 -> 35 | I49: =DATALOG!H96 -> 35 | J49: =DATALOG!I96 -> 35 | ... L49: =DATALOG!K96 -> 0
C50: =DATALOG!B97 -> Inventario final | D50: =DATALOG!C97 -> 425066 | E50: =DATALOG!D97 -> 416838 | F50: =DATALOG!E97 -> 431641 | G50: =DATALOG!F97 -> 414919 | H50: =DATALOG!G97 -> 300930 | I50: =DATALOG!H97 -> 185713 | J50: =DATALOG!I97 -> 139597 | ... L50: =DATALOG!K97 -> 0
C51: =DATALOG!B98 -> Cantidad producida este periodo | D51: =DATALOG!C98 -> 229019 | E51: =DATALOG!D98 -> 249303 | F51: =DATALOG!E98 -> 240113 | G51: =DATALOG!F98 -> 245822 | H51: =DATALOG!G98 -> 174855 | I51: =DATALOG!H98 -> 91478 | J51: =DATALOG!I98 -> 102594 | ... L51: =DATALOG!K98 -> 0
... C55: =DATALOG!B102 -> Gasto promedio en Responsabilidad Social | D55: =DATALOG!C102 -> 34414 | E55: =DATALOG!D102 -> 30668 | F55: =DATALOG!E102 -> 28581 | G55: =DATALOG!F102 -> 28979 | H55: =DATALOG!G102 -> 32784 | I55: =DATALOG!H102 -> 30079 | J55: =DATALOG!I102 -> 8750 | ... L55: =DATALOG!K102 -> 0
C58: =UPPER(DATALOG!B121) -> GASTOS HISTORICOS PROMEDIO CONSIDERANDO
D60: =DATALOG!C122 -> Alemania | E60: =DATALOG!D122 -> Australia | F60: =DATALOG!E122 -> Espana
C61: =DATALOG!B123 -> Mantencion de fabrica de Climatizacio | D61: =DATALOG!C123 -> 333780.3 | E61: =DATALOG!D123 -> 323381.1 | F61: =DATALOG!E123 -> 245009.7
C62: =DATALOG!B124 -> Mantencion de fabrica de Electrodomes | D62: =DATALOG!C124 -> 373919.7 | E62: =DATALOG!D124 -> 367900.8 | F62: =DATALOG!E124 -> 284640.3
C63: =DATALOG!B125 -> Publicidad para linea Climatizacio | D63: =DATALOG!C125 -> 100657.8 | E63: =DATALOG!D125 -> 113517.5 | F63: =DATALOG!E125 -> 106748.2
C64: =DATALOG!B126 -> Publicidad para linea Electrodomes | D64: =DATALOG!C126 -> 95255.5 | E64: =DATALOG!D126 -> 109668.6 | F64: =DATALOG!E126 -> 116667.8
C65: =DATALOG!B127 -> Comercializacion para linea Climatizacio | D65: =DATALOG!C127 -> 33807.8 | E65: =DATALOG!D127 -> 28645.6 | F65: =DATALOG!E127 -> 32175.8
C66: =DATALOG!B128 -> Comercializacion para linea Electrodomes | D66: =DATALOG!C128 -> 58330.2 | E66: =DATALOG!D128 -> 37893.5 | F66: =DATALOG!E128 -> 47362

Sheet Rentabilidad Linea 1
C3: =UPPER(DATALOG!B130) -> RENTABILIDAD POR ARTICULO DE CLIMATIZACIO
D4: =DATALOG!C131 -> Alemania | E4: =DATALOG!D131 -> Alemania | F4: =DATALOG!E131 -> Alemania | G4: =DATALOG!F131 -> Alemania | H4: =DATALOG!G131 -> Australia | I4: =DATALOG!H131 -> Australia | J4: =DATALOG!I131 -> Australia | K4: =DATALOG!J131 -> Australia | ... O4: =DATALOG!N131 -> Espana
D5: =DATALOG!C132 -> Prod. | E5: =DATALOG!D132 -> Inventario | F5: =DATALOG!E132 -> Industria | G5: =DATALOG!F132 -> Consumidor | H5: =DATALOG!G132 -> Prod. | I5: =DATALOG!H132 -> Inventario | J5: =DATALOG!I132 -> Industria | K5: =DATALOG!J132 -> Consumidor | ... O5: =DATALOG!N132 -> Consumidor
C6: =DATALOG!B131 -> Articulo | D6: =DATALOG!C133 -> Costo | E6: =DATALOG!D133 -> Valor | F6: =DATALOG!E133 -> Precio | G6: =DATALOG!F133 -> Precio | H6: =DATALOG!G133 -> Costo | I6: =DATALOG!H133 -> Valor | J6: =DATALOG!I133 -> Precio | K6: =DATALOG!J133 -> Precio | ... O6: =DATALOG!N133 -> Precio
C7: =DATALOG!B134 -> EstufaGas | D7: =DATALOG!C134 -> 25 | E7: =DATALOG!D134 -> 42 | F7: =DATALOG!E134 -> 62 | G7: =DATALOG!F134 -> 103 | H7: =DATALOG!G134 -> 28 | I7: =DATALOG!H134 -> 41 | J7: =DATALOG!I134 -> 56 | ... O7: =DATALOG!N134 -> 97
C8: =DATALOG!B135 -> EstufaElectr | D8: =DATALOG!C135 -> 32 | E8: =DATALOG!D135 -> 50 | F8: =DATALOG!E135 -> 72 | G8: =DATALOG!F135 -> 111 | H8: =DATALOG!G135 -> 36 | I8: =DATALOG!H135 -> 48 | J8: =DATALOG!I135 -> 74 | ... O8: =DATALOG!N135 -> 120
C9: =DATALOG!B136 -> VentPedestal | D9: =DATALOG!C136 -> 15 | E9: =DATALOG!D136 -> 17 | F9: =DATALOG!E136 -> 25 | G9: =DATALOG!F136 -> 35 | H9: =DATALOG!G136 -> 8 | I9: =DATALOG!H136 -> 20 | J9: =DATALOG!I136 -> 24 | ... O9: =DATALOG!N136 -> 40
C10: =DATALOG!B137 -> Vent_Torre | D10: =DATALOG!C137 -> 15 | E10: =DATALOG!D137 -> 23 | F10: =DATALOG!E137 -> 35 | G10: =DATALOG!F137 -> 53 | H10: =DATALOG!G137 -> 14 | I10: =DATALOG!H137 -> 26 | J10: =DATALOG!I137 -> 33 | ... O10: =DATALOG!N137 -> 55
C11: =DATALOG!B138 -> Purif_Aire | D11: =DATALOG!C138 -> 19 | E11: =DATALOG!D138 -> 32 | F11: =DATALOG!E138 -> 47 | G11: =DATALOG!F138 -> 79 | H11: =DATALOG!G138 -> 19 | I11: =DATALOG!H138 -> 37 | J11: =DATALOG!I138 -> 49 | ... O11: =DATALOG!N138 -> 87
C12: =DATALOG!B139 -> Deshumidific | D12: =DATALOG!C139 -> 22 | E12: =DATALOG!D139 -> 56 | F12: =DATALOG!E139 -> 57 | G12: =DATALOG!F139 -> 122 | H12: =DATALOG!G139 -> 23 | I12: =DATALOG!H139 -> 48 | J12: =DATALOG!I139 -> 67 | ... O12: =DATALOG!N139 -> 117
C13: =DATALOG!B140 -> Ionizador | D13: =DATALOG!C140 -> 15 | E13: =DATALOG!D140 -> 26 | F13: =DATALOG!E140 -> 35 | G13: =DATALOG!F140 -> 80 | H13: =DATALOG!G140 -> 16 | I13: =DATALOG!H140 -> 28 | J13: =DATALOG!I140 -> 39 | ... O13: =DATALOG!N140 -> 82
C14: =DATALOG!B141 -> 0 | D14: =DATALOG!C141 -> 0 | E14: =DATALOG!D141 -> 0 | F14: =DATALOG!E141 -> 0 | G14: =DATALOG!F141 -> 0 | H14: =DATALOG!G141 -> 0 | I14: =DATALOG!H141 -> 0 | J14: =DATALOG!I141 -> 0 | ... O14: =DATALOG!N141 -> 0
C15: =DATALOG!B142 -> 0 | D15: =DATALOG!C142 -> 0 | E15: =DATALOG!D142 -> 0 | F15: =DATALOG!E142 -> 0 | G15: =DATALOG!F142 -> 0 | H15: =DATALOG!G142 -> 0 | I15: =DATALOG!H142 -> 0 | J15: =DATALOG!I142 -> 0 | ... O15: =DATALOG!N142 -> 0

Sheet Rentabilidad Linea 2
C3: =UPPER(DATALOG!B144) -> RENTABILIDAD POR ARTICULO DE ELECTRODOMES
D4: =DATALOG!C145 -> Alemania | E4: =DATALOG!D145 -> Alemania | F4: =DATALOG!E145 -> Alemania | G4: =DATALOG!F145 -> Alemania | H4: =DATALOG!G145 -> Australia | I4: =DATALOG!H145 -> Australia | J4: =DATALOG!I145 -> Australia | K4: =DATALOG!J145 -> Australia | ... O4: =DATALOG!N145 -> Espana
D5: =DATALOG!C146 -> Prod. | E5: =DATALOG!D146 -> Inventario | F5: =DATALOG!E146 -> Industria | G5: =DATALOG!F146 -> Consumidor | H5: =DATALOG!G146 -> Prod. | I5: =DATALOG!H146 -> Inventario | J5: =DATALOG!I146 -> Industria | K5: =DATALOG!J146 -> Consumidor | ... O5: =DATALOG!N146 -> Consumidor
C6: =DATALOG!B145 -> Articulo | D6: =DATALOG!C147 -> Costo | E6: =DATALOG!D147 -> Valor | F6: =DATALOG!E147 -> Precio | G6: =DATALOG!F147 -> Precio | H6: =DATALOG!G147 -> Costo | I6: =DATALOG!H147 -> Valor | J6: =DATALOG!I147 -> Precio | K6: =DATALOG!J147 -> Precio | ... O6: =DATALOG!N147 -> Precio
C7: =DATALOG!B148 -> Hervidor | D7: =DATALOG!C148 -> 7 | E7: =DATALOG!D148 -> 13 | F7: =DATALOG!E148 -> 19 | G7: =DATALOG!F148 -> 32 | H7: =DATALOG!G148 -> 8 | I7: =DATALOG!H148 -> 17 | J7: =DATALOG!I148 -> 25 | ... O7: =DATALOG!N148 -> 29
C8: =DATALOG!B149 -> Tostador | D8: =DATALOG!C149 -> 5 | E8: =DATALOG!D149 -> 13 | F8: =DATALOG!E149 -> 19 | G8: =DATALOG!F149 -> 28 | H8: =DATALOG!G149 -> 6 | I8: =DATALOG!H149 -> 14 | J8: =DATALOG!I149 -> 23 | ... O8: =DATALOG!N149 -> 29
C9: =DATALOG!B150 -> Batidora | D9: =DATALOG!C150 -> 4 | E9: =DATALOG!D150 -> 10 | F9: =DATALOG!E150 -> 15 | G9: =DATALOG!F150 -> 28 | H9: =DATALOG!G150 -> 4 | I9: =DATALOG!H150 -> 12 | J9: =DATALOG!I150 -> 17 | ... O9: =DATALOG!N150 -> 26
C10: =DATALOG!B151 -> Cafetera | D10: =DATALOG!C151 -> 9 | E10: =DATALOG!D151 -> 15 | F10: =DATALOG!E151 -> 24 | G10: =DATALOG!F151 -> 38 | H10: =DATALOG!G151 -> 9 | I10: =DATALOG!H151 -> 19 | J10: =DATALOG!I151 -> 29 | ... O10: =DATALOG!N151 -> 33
C11: =DATALOG!B152 -> Licuadora | D11: =DATALOG!C152 -> 8 | E11: =DATALOG!D152 -> 16 | F11: =DATALOG!E152 -> 26 | G11: =DATALOG!F152 -> 41 | H11: =DATALOG!G152 -> 9 | I11: =DATALOG!H152 -> 19 | J11: =DATALOG!I152 -> 28 | ... O11: =DATALOG!N152 -> 35
C12: =DATALOG!B153 -> FreidoraAire | D12: =DATALOG!C153 -> 9 | E12: =DATALOG!D153 -> 25 | F12: =DATALOG!E153 -> 30 | G12: =DATALOG!F153 -> 65 | H12: =DATALOG!G153 -> 12 | I12: =DATALOG!H153 -> 27 | J12: =DATALOG!I153 -> 37 | ... O12: =DATALOG!N153 -> 61
C13: =DATALOG!B154 -> ParrilaElect | D13: =DATALOG!C154 -> 8 | E13: =DATALOG!D154 -> 17 | F13: =DATALOG!E154 -> 28 | G13: =DATALOG!F154 -> 56 | H13: =DATALOG!G154 -> 10 | I13: =DATALOG!H154 -> 17 | J13: =DATALOG!I154 -> 39 | ... O13: =DATALOG!N154 -> 53
C14: =DATALOG!B155 -> 0 | D14: =DATALOG!C155 -> 0 | E14: =DATALOG!D155 -> 0 | F14: =DATALOG!E155 -> 0 | G14: =DATALOG!F155 -> 0 | H14: =DATALOG!G155 -> 0 | I14: =DATALOG!H155 -> 0 | J14: =DATALOG!I155 -> 0 | ... O14: =DATALOG!N155 -> 0
C15: =DATALOG!B156 -> 0 | D15: =DATALOG!C156 -> 0 | E15: =DATALOG!D156 -> 0 | F15: =DATALOG!E156 -> 0 | G15: =DATALOG!F156 -> 0 | H15: =DATALOG!G156 -> 0 | I15: =DATALOG!H156 -> 0 | J15: =DATALOG!I156 -> 0 | ... O15: =DATALOG!N156 -> 0

Sheet Precios Promedios
C3: =UPPER(DATALOG!B103) -> PRECIOS DE EXPEDITAJE (NO SE RECOMIENDA USAR ESTOS COMO REFERENCIA PARA DETERMINAR PRECIOS
C5: =DATALOG!B104 -> Articulo | D5: =DATALOG!C104 -> EstufaGas | E5: =DATALOG!D104 -> EstufaElectr | F5: =DATALOG!E104 -> VentPedestal | G5: =DATALOG!F104 -> Vent_Torre | H5: =DATALOG!G104 -> Purif_Aire | I5: =DATALOG!H104 -> Deshumidific | J5: =DATALOG!I104 -> Ionizador | ... L5: =DATALOG!K104 -> 0
C6: =DATALOG!B105 -> Climatizacio in Alemania | D6: =DATALOG!C105 -> 144 | E6: =DATALOG!D105 -> 163.8 | F6: =DATALOG!E105 -> 50 | G6: =DATALOG!F105 -> 71.2 | H6: =DATALOG!G105 -> 111.2 | I6: =DATALOG!H105 -> 183 | J6: =DATALOG!I105 -> 120 | ... L6: =DATALOG!K105 -> 0
C7: =DATALOG!B106 -> Climatizacio in Australia | D7: =DATALOG!C106 -> 144.8 | E7: =DATALOG!D106 -> 192.2 | F7: =DATALOG!E106 -> 62 | G7: =DATALOG!F106 -> 87.5 | H7: =DATALOG!G106 -> 122.8 | I7: =DATALOG!H106 -> 183 | J7: =DATALOG!I106 -> 120 | ... L7: =DATALOG!K106 -> 0
C8: =DATALOG!B107 -> Climatizacio in Espana | D8: =DATALOG!C107 -> 137.2 | E8: =DATALOG!D107 -> 170.2 | F8: =DATALOG!E107 -> 58 | G8: =DATALOG!F107 -> 80 | H8: =DATALOG!G107 -> 122.5 | I8: =DATALOG!H107 -> 175.5 | J8: =DATALOG!I107 -> 123 | ... L8: =DATALOG!K107 -> 0
C10: =DATALOG!B108 -> Articulo | D10: =DATALOG!C108 -> Hervidor | E10: =DATALOG!D108 -> Tostador | F10: =DATALOG!E108 -> Batidora | G10: =DATALOG!F108 -> Cafetera | H10: =DATALOG!G108 -> Licuadora | I10: =DATALOG!H108 -> FreidoraAire | J10: =DATALOG!I108 -> ParrilaElect | ... L10: =DATALOG!K108 -> 0
C11: =DATALOG!B109 -> Electrodomes in Alemania | D11: =DATALOG!C109 -> 45.5 | E11: =DATALOG!D109 -> 39.5 | F11: =DATALOG!E109 -> 40.2 | G11: =DATALOG!F109 -> 53.8 | H11: =DATALOG!G109 -> 57 | I11: =DATALOG!H109 -> 97.5 | J11: =DATALOG!I109 -> 84 | ... L11: =DATALOG!K109 -> 0
C12: =DATALOG!B110 -> Electrodomes in Australia | D12: =DATALOG!C110 -> 52 | E12: =DATALOG!D110 -> 50 | F12: =DATALOG!E110 -> 40.5 | G12: =DATALOG!F110 -> 67.2 | H12: =DATALOG!G110 -> 71.2 | I12: =DATALOG!H110 -> 97.5 | J12: =DATALOG!I110 -> 75 | ... L12: =DATALOG!K110 -> 0
C13: =DATALOG!B111 -> Electrodomes in Espana | D13: =DATALOG!C111 -> 41.2 | E13: =DATALOG!D111 -> 40 | F13: =DATALOG!E111 -> 35.8 | G13: =DATALOG!F111 -> 46 | H13: =DATALOG!G111 -> 47.2 | I13: =DATALOG!H111 -> 91.5 | J13: =DATALOG!I111 -> 79.5 | ... L13: =DATALOG!K111 -> 0
C15: =UPPER(DATALOG!B112) -> PRECIOS DE COMPRAS DE SALDOS
C17: =DATALOG!B113 -> Articulo | D17: =DATALOG!C113 -> EstufaGas | E17: =DATALOG!D113 -> EstufaElectr | F17: =DATALOG!E113 -> VentPedestal | G17: =DATALOG!F113 -> Vent_Torre | H17: =DATALOG!G113 -> Purif_Aire | I17: =DATALOG!H113 -> Deshumidific | J17: =DATALOG!I113 -> Ionizador | ... L17: =DATALOG!K113 -> 0
C18: =DATALOG!B114 -> Climatizacio in Alemania | D18: =DATALOG!C114 -> 26 | E18: =DATALOG!D114 -> 33 | F18: =DATALOG!E114 -> 9 | G18: =DATALOG!F114 -> 15 | H18: =DATALOG!G114 -> 20 | I18: =DATALOG!H114 -> 25 | J18: =DATALOG!I114 -> 17 | ... L18: =DATALOG!K114 -> 0
C19: =DATALOG!B115 -> Climatizacio in Australia | D19: =DATALOG!C115 -> 26 | E19: =DATALOG!D115 -> 33 | F19: =DATALOG!E115 -> 9 | G19: =DATALOG!F115 -> 15 | H19: =DATALOG!G115 -> 20 | I19: =DATALOG!H115 -> 25 | J19: =DATALOG!I115 -> 17 | ... L19: =DATALOG!K115 -> 0
C20: =DATALOG!B116 -> Climatizacio in Espana | D20: =DATALOG!C116 -> 26 | E20: =DATALOG!D116 -> 33 | F20: =DATALOG!E116 -> 9 | G20: =DATALOG!F116 -> 15 | H20: =DATALOG!G116 -> 20 | I20: =DATALOG!H116 -> 25 | J20: =DATALOG!I116 -> 17 | ... L20: =DATALOG!K116 -> 0
C22: =DATALOG!B117 -> Articulo | D22: =DATALOG!C117 -> Hervidor | E22: =DATALOG!D117 -> Tostador | F22: =DATALOG!E117 -> Batidora | G22: =DATALOG!F117 -> Cafetera | H22: =DATALOG!G117 -> Licuadora | I22: =DATALOG!H117 -> FreidoraAire | J22: =DATALOG!I117 -> ParrilaElect | ... L22: =DATALOG!K117 -> 0
C23: =DATALOG!B118 -> Electrodomes in Alemania | D23: =DATALOG!C118 -> 6 | E23: =DATALOG!D118 -> 5 | F23: =DATALOG!E118 -> 3 | G23: =DATALOG!F118 -> 8 | H23: =DATALOG!G118 -> 8 | I23: =DATALOG!H118 -> 10 | J23: =DATALOG!I118 -> 9 | ... L23: =DATALOG!K118 -> 0
C24: =DATALOG!B119 -> Electrodomes in Australia | D24: =DATALOG!C119 -> 6 | E24: =DATALOG!D119 -> 5 | F24: =DATALOG!E119 -> 3 | G24: =DATALOG!F119 -> 8 | H24: =DATALOG!G119 -> 8 | I24: =DATALOG!H119 -> 10 | J24: =DATALOG!I119 -> 9 | ... L24: =DATALOG!K119 -> 0
C25: =DATALOG!B120 -> Electrodomes in Espana | D25: =DATALOG!C120 -> 6 | E25: =DATALOG!D120 -> 5 | F25: =DATALOG!E120 -> 3 | G25: =DATALOG!F120 -> 8 | H25: =DATALOG!G120 -> 8 | I25: =DATALOG!H120 -> 10 | J25: =DATALOG!I120 -> 9 | ... L25: =DATALOG!K120 -> 0

Sheet Vta Industria Linea 1
C3: =UPPER(CONCATENATE(DATALOG!B324," PARA ",DATALOG!B325)) -> PRECIO PROMEDIO TRANSADO ENTRE EMPRESAS POR ARTICULO Y CANTIDAD PARA EL PERIODO 7 SEGUN EL TRANSPORTE. PARA CLIMATIZACIO
D5: =DATALOG!E325 -> Alemania | F5: =DATALOG!G325 -> Australia | H5: =DATALOG!I325 -> Espana | J5: =DATALOG!L325 -> 0 | L5: =DATALOG!N325 -> 0 | N5: =DATALOG!P325 -> 0
D6: =DATALOG!E326 -> A 1 periodo | F6: =DATALOG!G326 -> A 1 periodo | H6: =DATALOG!I326 -> A 1 periodo | J6: =DATALOG!L326 -> 0 | L6: =DATALOG!N326 -> 0 | N6: =DATALOG!P326 -> 0
D7: =DATALOG!D327 -> Precio | E7: =DATALOG!E327 -> Cantidad | F7: =DATALOG!F327 -> Precio | G7: =DATALOG!G327 -> Cantidad | H7: =DATALOG!H327 -> Precio | I7: =DATALOG!I327 -> Cantidad | J7: =DATALOG!J327 -> 0 | K7: =DATALOG!K327 -> 0 | ... O7: =DATALOG!O327 -> 0
C8: =DATALOG!B328 -> EstufaGas | D8: =DATALOG!D328 -> 62.3 | E8: =DATALOG!E328 -> 92687 | F8: =DATALOG!F328 -> 56.2 | G8: =DATALOG!G328 -> 17488 | H8: =DATALOG!H328 -> 59.3 | I8: =DATALOG!I328 -> 128603 | J8: =DATALOG!J328 -> 0 | K8: =DATALOG!K328 -> 0 | ... O8: =DATALOG!O328 -> 0
C9: =DATALOG!B329 -> EstufaElectr | D9: =DATALOG!D329 -> 72.3 | E9: =DATALOG!E329 -> 133806 | F9: =DATALOG!F329 -> 73.6 | G9: =DATALOG!G329 -> 34678 | H9: =DATALOG!H329 -> 73 | I9: =DATALOG!I329 -> 99340 | J9: =DATALOG!J329 -> 0 | K9: =DATALOG!K329 -> 0 | ... O9: =DATALOG!O329 -> 0
C10: =DATALOG!B330 -> VentPedestal | D10: =DATALOG!D330 -> 25.1 | E10: =DATALOG!E330 -> 65279 | F10: =DATALOG!F330 -> 24.2 | G10: =DATALOG!G330 -> 176128 | H10: =DATALOG!H330 -> 21.9 | I10: =DATALOG!I330 -> 47926 | J10: =DATALOG!J330 -> 0 | K10: =DATALOG!K330 -> 0 | ... O10: =DATALOG!O330 -> 0
C11: =DATALOG!B331 -> Vent_Torre | D11: =DATALOG!D331 -> 35.4 | E11: =DATALOG!E331 -> 72776 | F11: =DATALOG!F331 -> 33.3 | G11: =DATALOG!G331 -> 178465 | H11: =DATALOG!H331 -> 35.1 | I11: =DATALOG!I331 -> 42270 | J11: =DATALOG!J331 -> 0 | K11: =DATALOG!K331 -> 0 | ... O11: =DATALOG!O331 -> 0
C12: =DATALOG!B332 -> Purif_Aire | D12: =DATALOG!D332 -> 47 | E12: =DATALOG!E332 -> 112752 | F12: =DATALOG!F332 -> 48.7 | G12: =DATALOG!G332 -> 129750 | H12: =DATALOG!H332 -> 48.4 | I12: =DATALOG!I332 -> 111893 | J12: =DATALOG!J332 -> 0 | K12: =DATALOG!K332 -> 0 | ... O12: =DATALOG!O332 -> 0
C13: =DATALOG!B333 -> Deshumidific | D13: =DATALOG!D333 -> 57.1 | E13: =DATALOG!E333 -> 9672 | F13: =DATALOG!F333 -> 66.8 | G13: =DATALOG!G333 -> 39499 | H13: =DATALOG!H333 -> 57.5 | I13: =DATALOG!I333 -> 21375 | J13: =DATALOG!J333 -> 0 | K13: =DATALOG!K333 -> 0 | ... O13: =DATALOG!O333 -> 0
C14: =DATALOG!B334 -> Ionizador | D14: =DATALOG!D334 -> 35 | E14: =DATALOG!E334 -> 18201 | F14: =DATALOG!F334 -> 38.5 | G14: =DATALOG!G334 -> 33500 | H14: =DATALOG!H334 -> 40.2 | I14: =DATALOG!I334 -> 30890 | J14: =DATALOG!J334 -> 0 | K14: =DATALOG!K334 -> 0 | ... O14: =DATALOG!O334 -> 0
C15: =DATALOG!B335 -> 0 | D15: =DATALOG!D335 -> 0 | E15: =DATALOG!E335 -> 0 | F15: =DATALOG!F335 -> 0 | G15: =DATALOG!G335 -> 0 | H15: =DATALOG!H335 -> 0 | I15: =DATALOG!I335 -> 0 | J15: =DATALOG!J335 -> 0 | K15: =DATALOG!K335 -> 0 | ... O15: =DATALOG!O335 -> 0
C16: =DATALOG!B336 -> 0 | D16: =DATALOG!D336 -> 0 | E16: =DATALOG!E336 -> 0 | F16: =DATALOG!F336 -> 0 | G16: =DATALOG!G336 -> 0 | H16: =DATALOG!H336 -> 0 | I16: =DATALOG!I336 -> 0 | J16: =DATALOG!J336 -> 0 | K16: =DATALOG!K336 -> 0 | ... O16: =DATALOG!O336 -> 0

Sheet Vta Industria Linea 2
C3: =UPPER(CONCATENATE(DATALOG!B324," PARA ",DATALOG!B337)) -> PRECIO PROMEDIO TRANSADO ENTRE EMPRESAS POR ARTICULO Y CANTIDAD PARA EL PERIODO 7 SEGUN EL TRANSPORTE. PARA ELECTRODOMES
D5: =DATALOG!E337 -> Alemania | F5: =DATALOG!G337 -> Australia | H5: =DATALOG!I337 -> Espana | J5: =DATALOG!L337 -> 0 | L5: =DATALOG!N337 -> 0 | N5: =DATALOG!P337 -> 0
D6: =DATALOG!E338 -> A 1 periodo | F6: =DATALOG!G338 -> A 1 periodo | H6: =DATALOG!I338 -> A 1 periodo | J6: =DATALOG!L338 -> 0 | L6: =DATALOG!N338 -> 0 | N6: =DATALOG!P338 -> 0
D7: =DATALOG!D339 -> Precio | E7: =DATALOG!E339 -> Cantidad | F7: =DATALOG!F339 -> Precio | G7: =DATALOG!G339 -> Cantidad | H7: =DATALOG!H339 -> Precio | I7: =DATALOG!I339 -> Cantidad | J7: =DATALOG!J339 -> 0 | K7: =DATALOG!K339 -> 0 | ... O7: =DATALOG!O339 -> 0
C8: =DATALOG!B340 -> Hervidor | D8: =DATALOG!D340 -> 19.3 | E8: =DATALOG!E340 -> 182355 | F8: =DATALOG!F340 -> 24.8 | G8: =DATALOG!G340 -> 113911 | H8: =DATALOG!H340 -> 18.8 | I8: =DATALOG!I340 -> 145422 | J8: =DATALOG!J340 -> 0 | K8: =DATALOG!K340 -> 0 | ... O8: =DATALOG!O340 -> 0
C9: =DATALOG!B341 -> Tostador | D9: =DATALOG!D341 -> 18.6 | E9: =DATALOG!E341 -> 150939 | F9: =DATALOG!F341 -> 22.6 | G9: =DATALOG!G341 -> 84489 | H9: =DATALOG!H341 -> 17.6 | I9: =DATALOG!I341 -> 175888 | J9: =DATALOG!J341 -> 0 | K9: =DATALOG!K341 -> 0 | ... O9: =DATALOG!O341 -> 0
C10: =DATALOG!B342 -> Batidora | D10: =DATALOG!D342 -> 15.1 | E10: =DATALOG!E342 -> 181003 | F10: =DATALOG!F342 -> 17.4 | G10: =DATALOG!G342 -> 97434 | H10: =DATALOG!H342 -> 14.6 | I10: =DATALOG!I342 -> 179098 | J10: =DATALOG!J342 -> 0 | K10: =DATALOG!K342 -> 0 | ... O10: =DATALOG!O342 -> 0
C11: =DATALOG!B343 -> Cafetera | D11: =DATALOG!D343 -> 23.6 | E11: =DATALOG!E343 -> 177512 | F11: =DATALOG!F343 -> 29 | G11: =DATALOG!G343 -> 93468 | H11: =DATALOG!H343 -> 22.8 | I11: =DATALOG!I343 -> 139342 | J11: =DATALOG!J343 -> 0 | K11: =DATALOG!K343 -> 0 | ... O11: =DATALOG!O343 -> 0
C12: =DATALOG!B344 -> Licuadora | D12: =DATALOG!D344 -> 26.4 | E12: =DATALOG!E344 -> 83781 | F12: =DATALOG!F344 -> 28.4 | G12: =DATALOG!G344 -> 85431 | H12: =DATALOG!H344 -> 22.1 | I12: =DATALOG!I344 -> 93523 | J12: =DATALOG!J344 -> 0 | K12: =DATALOG!K344 -> 0 | ... O12: =DATALOG!O344 -> 0
C13: =DATALOG!B345 -> FreidoraAire | D13: =DATALOG!D345 -> 30.4 | E13: =DATALOG!E345 -> 27566 | F13: =DATALOG!F345 -> 36.7 | G13: =DATALOG!G345 -> 38731 | H13: =DATALOG!H345 -> 33 | I13: =DATALOG!I345 -> 45930 | J13: =DATALOG!J345 -> 0 | K13: =DATALOG!K345 -> 0 | ... O13: =DATALOG!O345 -> 0
C14: =DATALOG!B346 -> ParrilaElect | D14: =DATALOG!D346 -> 28.4 | E14: =DATALOG!E346 -> 32641 | F14: =DATALOG!F346 -> 39 | G14: =DATALOG!G346 -> 11363 | H14: =DATALOG!H346 -> 24.6 | I14: =DATALOG!I346 -> 51294 | J14: =DATALOG!J346 -> 0 | K14: =DATALOG!K346 -> 0 | ... O14: =DATALOG!O346 -> 0
C15: =DATALOG!B347 -> 0 | D15: =DATALOG!D347 -> 0 | E15: =DATALOG!E347 -> 0 | F15: =DATALOG!F347 -> 0 | G15: =DATALOG!G347 -> 0 | H15: =DATALOG!H347 -> 0 | I15: =DATALOG!I347 -> 0 | J15: =DATALOG!J347 -> 0 | K15: =DATALOG!K347 -> 0 | ... O15: =DATALOG!O347 -> 0
C16: =DATALOG!B348 -> 0 | D16: =DATALOG!D348 -> 0 | E16: =DATALOG!E348 -> 0 | F16: =DATALOG!F348 -> 0 | G16: =DATALOG!G348 -> 0 | H16: =DATALOG!H348 -> 0 | I16: =DATALOG!I348 -> 0 | J16: =DATALOG!J348 -> 0 | K16: =DATALOG!K348 -> 0 | ... O16: =DATALOG!O348 -> 0

Sheet Actividad Empresas
C3: EMPRESAS CON ACTIVIDAD
C5: =+DATALOG!C350 -> Retailers | D5: =+DATALOG!D350 -> Retailers | E5: =+DATALOG!E350 -> Retailers | F5: =+DATALOG!F350 -> Productores | G5: =+DATALOG!G350 -> Productores | H5: =+DATALOG!H350 -> Productores
C6: =+DATALOG!C351 -> Alemania | D6: =+DATALOG!D351 -> Australia | E6: =+DATALOG!E351 -> Espana | F6: =+DATALOG!F351 -> Alemania | G6: =+DATALOG!G351 -> Australia | H6: =+DATALOG!H351 -> Espana
C7: =IF(DATALOG!C352=0,"",DATALOG!C352) -> 2 | D7: =IF(DATALOG!D352=0,"",DATALOG!D352) -> 4 | E7: =IF(DATALOG!E352=0,"",DATALOG!E352) -> 2 | F7: =IF(DATALOG!F352=0,"",DATALOG!F352) -> 3 | G7: =IF(DATALOG!G352=0,"",DATALOG!G352) -> 2 | H7: =IF(DATALOG!H352=0,"",DATALOG!H352) -> 6
C8: =IF(DATALOG!C353=0,"",DATALOG!C353) -> 7 | D8: =IF(DATALOG!D353=0,"",DATALOG!D353) -> 5 | E8: =IF(DATALOG!E353=0,"",DATALOG!E353) -> 3 | F8: =IF(DATALOG!F353=0,"",DATALOG!F353) -> 5 | G8: =IF(DATALOG!G353=0,"",DATALOG!G353) -> 3 | H8: =IF(DATALOG!H353=0,"",DATALOG!H353) -> 7
C9: =IF(DATALOG!C354=0,"",DATALOG!C354) -> 9 | D9: =IF(DATALOG!D354=0,"",DATALOG!D354) -> 10 | E9: =IF(DATALOG!E354=0,"",DATALOG!E354) -> 4 | F9: =IF(DATALOG!F354=0,"",DATALOG!F354) -> 8 | G9: =IF(DATALOG!G354=0,"",DATALOG!G354) -> 6 | H9: =IF(DATALOG!H354=0,"",DATALOG!H354) -> 9
C10: =IF(DATALOG!C355=0,"",DATALOG!C355) -> 10 | D10: =IF(DATALOG!D355=0,"",DATALOG!D355) -> 11 | E10: =IF(DATALOG!E355=0,"",DATALOG!E355) -> 8 | F10: =IF(DATALOG!F355=0,"",DATALOG!F355) -> 14 | G10: =IF(DATALOG!G355=0,"",DATALOG!G355) -> 7 | H10: =IF(DATALOG!H355=0,"",DATALOG!H355) -> 10
C11: =IF(DATALOG!C356=0,"",DATALOG!C356) -> 12 | D11: =IF(DATALOG!D356=0,"",DATALOG!D356) -> 12 | E11: =IF(DATALOG!E356=0,"",DATALOG!E356) -> 16 | F11: =IF(DATALOG!F356=0,"",DATALOG!F356) -> 16 | G11: =IF(DATALOG!G356=0,"",DATALOG!G356) -> 9 | H11: =IF(DATALOG!H356=0,"",DATALOG!H356) -> 11
C12: =IF(DATALOG!C357=0,"",DATALOG!C357) -> 13 | D12: =IF(DATALOG!D357=0,"",DATALOG!D357) -> 14 | E12: =IF(DATALOG!E357=0,"",DATALOG!E357) -> 17 | F12: =IF(DATALOG!F357=0,"",DATALOG!F357) -> 17 | G12: =IF(DATALOG!G357=0,"",DATALOG!G357) -> 13 | H12: =IF(DATALOG!H357=0,"",DATALOG!H357) -> 12
C13: =IF(DATALOG!C358=0,"",DATALOG!C358) -> 15 | D13: =IF(DATALOG!D358=0,"",DATALOG!D358) -> 17 | E13: =IF(DATALOG!E358=0,"",DATALOG!E358) -> 20 | F13: =IF(DATALOG!F358=0,"",DATALOG!F358) -> 20 | G13: =IF(DATALOG!G358=0,"",DATALOG!G358) -> 15 | H13: =IF(DATALOG!H358=0,"",DATALOG!H358) -> 13
C14: =IF(DATALOG!C359=0,"",DATALOG!C359) -> 18 | D14: =IF(DATALOG!D359=0,"",DATALOG!D359) -> 18 | E14: =IF(DATALOG!E359=0,"",DATALOG!E359) -> 21 | F14: =IF(DATALOG!F359=0,"",DATALOG!F359) -> 21 | G14: =IF(DATALOG!G359=0,"",DATALOG!G359) -> 16 | H14: =IF(DATALOG!H359=0,"",DATALOG!H359) -> 14
C15: =IF(DATALOG!C360=0,"",DATALOG!C360) -> 19 | D15: =IF(DATALOG!D360=0,"",DATALOG!D360) -> 21 | E15: =IF(DATALOG!E360=0,"",DATALOG!E360) -> 23 | F15: =IF(DATALOG!F360=0,"",DATALOG!F360) -> 24 | G15: =IF(DATALOG!G360=0,"",DATALOG!G360) -> 19 | H15: =IF(DATALOG!H360=0,"",DATALOG!H360) -> 15
C16: =IF(DATALOG!C361=0,"",DATALOG!C361) -> 23 | D16: =IF(DATALOG!D361=0,"",DATALOG!D361) -> 22 | E16: =IF(DATALOG!E361=0,"",DATALOG!E361) -> 24 | F16: =IF(DATALOG!F361=0,"",DATALOG!F361) -> 32 | G16: =IF(DATALOG!G361=0,"",DATALOG!G361) -> 20 | H16: =IF(DATALOG!H361=0,"",DATALOG!H361) -> 18
C17: =IF(DATALOG!C362=0,"",DATALOG!C362) -> 27 | D17: =IF(DATALOG!D362=0,"",DATALOG!D362) -> 24 | E17: =IF(DATALOG!E362=0,"",DATALOG!E362) -> 26 | F17: =IF(DATALOG!F362=0,"",DATALOG!F362) -> 35 | G17: =IF(DATALOG!G362=0,"",DATALOG!G362) -> 23 | H17: =IF(DATALOG!H362=0,"",DATALOG!H362) -> 19
C18: =IF(DATALOG!C363=0,"",DATALOG!C363) -> 28 | D18: =IF(DATALOG!D363=0,"",DATALOG!D363) -> 25 | E18: =IF(DATALOG!E363=0,"",DATALOG!E363) -> 29 | F18: =IF(DATALOG!F363=0,"",DATALOG!F363) -> 36 | G18: =IF(DATALOG!G363=0,"",DATALOG!G363) -> 26 | H18: =IF(DATALOG!H363=0,"",DATALOG!H363) -> 22
... C305: =IF(DATALOG!C650=0,"",DATALOG!C650) | D305: =IF(DATALOG!D650=0,"",DATALOG!D650) | E305: =IF(DATALOG!E650=0,"",DATALOG!E650) | F305: =IF(DATALOG!F650=0,"",DATALOG!F650) | G305: =IF(DATALOG!G650=0,"",DATALOG!G650) | H305: =IF(DATALOG!H650=0,"",DATALOG!H650)

Sheet Fabricas sin Uso
C2: FABRICAS QUE NO HAN SIDO UTILIZADAS EL ULTIMO PERIODO
C4: Alemania : Empresas con Climatizacio fabrica que no produjo el periodo anterior | D4: (Numero de compania y edad de la fabrica)
D5: 98 | E5: 3
C7: Australia : Empresas con Climatizacio fabrica que no produjo el periodo anterior | D7: (Numero de compania y edad de la fabrica)
D8: 3 | E8: 4
C10: Espana : Empresas con Climatizacio fabrica que no produjo el periodo anterior | D10: (Numero de compania y edad de la fabrica)
D11: 99 | E11: 3
C13: Alemania : Empresas con Electrodomes fabrica que no produjo el periodo anterior | D13: (Numero de compania y edad de la fabrica)
D14: 67 | E14: 3
D15: 98 | E15: 3
C17: Australia : Empresas con Electrodomes fabrica que no produjo el periodo anterior | D17: (Numero de compania y edad de la fabrica)
C19: Espana : Empresas con Electrodomes fabrica que no produjo el periodo anterior | D19: (Numero de compania y edad de la fabrica)
D20: 103 | E20: 2
D21: 105 | E21: 3

Sheet DATALOG
A1: 1 | B1: Informacion detallada de Alemania para Climatizacio hasta el periodo 7.
A2: 1 | B2: Pais | C2: Alemania | D2: Alemania | E2: Alemania | F2: Alemania | G2: Alemania | H2: Alemania | I2: Alemania
A3: 1 | B3: Lineas de Productos | C3: Climatizacio | D3: Climatizacio | E3: Climatizacio | F3: Climatizacio | G3: Climatizacio | H3: Climatizacio | I3: Climatizacio
A4: 1 | B4: Articulo | C4: EstufaGas | D4: EstufaElectr | E4: VentPedestal | F4: Vent_Torre | G4: Purif_Aire | H4: Deshumidific | I4: Ionizador
A5: 1 | B5: Precio promedio historico unidades vendidas a consumidores | C5: 96 | D5: 109.17 | E5: 33.33 | F5: 47.5 | G5: 74.17 | H5: 122 | I5: 80
A6: 1 | B6: Variacion de precio respecto periodo anterior (%) | C6: 0.062 | D6: 0.018 | E6: 0.029 | F6: 0.104 | G6: 0.039 | H6: 0 | I6: 0
A7: 1 | B7: Precio que consumidores estan dispuestos a pagar | C7: 104 | D7: 116 | E7: 34 | F7: 51 | G7: 80 | H7: 120 | I7: 80
A8: 1 | B8: Precio promedio ofrecido a consumidores en periodo 7 | C8: 103 | D8: 111 | E8: 35 | F8: 53 | G8: 79 | H8: 122 | I8: 80
A9: 1 | B9: Ventas a consumidores total | C9: 99459 | D9: 109066 | E9: 69566 | F9: 65213 | G9: 100754 | H9: 46920 | I9: 2000
A10: 1 | B10: Empresas vendiendo a consumidores | C10: 23 | D10: 24 | E10: 23 | F10: 19 | G10: 28 | H10: 13 | I10: 1
A11: 1 | B11: Empresas presentes en mcdo. consumidores con linea de productos | C11: 38 | D11: 38 | E11: 38 | F11: 38 | G11: 38 | H11: 38 | I11: 38
A12: 1 | B12: Inventario final | C12: 289245 | D12: 281434 | E12: 294198 | F12: 370214 | G12: 433254 | H12: 117180 | I12: 79983
A13: 1 | B13: Cantidad producida este periodo | C13: 131308 | D13: 128875 | E13: 200481 | F13: 253714 | G13: 274318 | H13: 19500 | I13: 43959
A14: 1 | B14: Gasto promedio en publicidad y promociones | C14: 86235 | D14: 97492 | E14: 82326 | F14: 87800 | G14: 75750 | H14: 113631 | I14: 79400
A15: 1 | B15: Gasto promedio en Servicio Post-Venta | C15: 29946 | D15: 36188 | E15: 29500 | F15: 36789 | G15: 30902 | H15: 41250 | I15: 24250
A16: 1 | B16: Promedio de Puntos de Venta | C16: 2 | D16: 2 | E16: 2 | F16: 2 | G16: 2 | H16: 2 | I16: 1
A17: 1 | B17: Gasto promedio en Responsabilidad Social | C17: 23154 | D17: 26882 | E17: 21586 | F17: 23215 | G17: 22546 | H17: 27433 | I17: 781
A18: 2 | B18: Informacion detallada de Australia para Climatizacio hasta el periodo 7.
A19: 2 | B19: Pais | C19: Australia | D19: Australia | E19: Australia | F19: Australia | G19: Australia | H19: Australia | I19: Australia
A20: 2 | B20: Lineas de Productos | C20: Climatizacio | D20: Climatizacio | E20: Climatizacio | F20: Climatizacio | G20: Climatizacio | H20: Climatizacio | I20: Climatizacio
A21: 2 | B21: Articulo | C21: EstufaGas | D21: EstufaElectr | E21: VentPedestal | F21: Vent_Torre | G21: Purif_Aire | H21: Deshumidific | I21: Ionizador
A22: 2 | B22: Precio promedio historico unidades vendidas a consumidores | C22: 96.5 | D22: 128.17 | E22: 41.33 | F22: 58.33 | G22: 81.83 | H22: 122 | I22: 80
A23: 2 | B23: Variacion de precio respecto periodo anterior (%) | C23: 0.04 | D23: -0.023 | E23: 0.048 | F23: 0.051 | G23: 0.012 | H23: 0 | I23: 0
A24: 2 | B24: Precio que consumidores estan dispuestos a pagar | C24: 103 | D24: 134 | E24: 44 | F24: 62 | G24: 88 | H24: 115 | I24: 80
A25: 2 | B25: Precio promedio ofrecido a consumidores en periodo 7 | C25: 104 | D25: 129 | E25: 44 | F25: 62 | G25: 86 | H25: 122 | I25: 80
A26: 2 | B26: Ventas a consumidores total | C26: 44719 | D26: 34434 | E26: 165788 | F26: 143347 | G26: 152006 | H26: 38328 | I26: 2784
A27: 2 | B27: Empresas vendiendo a consumidores | C27: 14 | D27: 12 | E27: 30 | F27: 25 | G27: 27 | H27: 7 | I27: 1
A28: 2 | B28: Empresas presentes en mcdo. consumidores con linea de productos | C28: 35 | D28: 35 | E28: 35 | F28: 35 | G28: 35 | H28: 35 | I28: 35
A29: 2 | B29: Inventario final | C29: 177790 | D29: 196372 | E29: 396410 | F29: 491533 | G29: 382583 | H29: 133033 | I29: 107490
A30: 2 | B30: Cantidad producida este periodo | C30: 127607 | D30: 132590 | E30: 99175 | F30: 187502 | G30: 148144 | H30: 37947 | I30: 51525
A31: 2 | B31: Gasto promedio en publicidad y promociones | C31: 95286 | D31: 98658 | E31: 87423 | F31: 97532 | G31: 93807 | H31: 104786 | I31: 134500
A32: 2 | B32: Gasto promedio en Servicio Post-Venta | C32: 47321 | D32: 50458 | E32: 45167 | F32: 47240 | G32: 46981 | H32: 53571 | I32: 0
A33: 2 | B33: Promedio de Puntos de Venta | C33: 3 | D33: 3 | E33: 3 | F33: 3 | G33: 3 | H33: 3 | I33: 1
A34: 2 | B34: Gasto promedio en Responsabilidad Social | C34: 32824 | D34: 34460 | E34: 28437 | F34: 28483 | G34: 30254 | H34: 24799 | I34: 0
A35: 3 | B35: Informacion detallada de Espana para Climatizacio hasta el periodo 7.
A36: 3 | B36: Pais | C36: Espana | D36: Espana | E36: Espana | F36: Espana | G36: Espana | H36: Espana | I36: Espana
A37: 3 | B37: Lineas de Productos | C37: Climatizacio | D37: Climatizacio | E37: Climatizacio | F37: Climatizacio | G37: Climatizacio | H37: Climatizacio | I37: Climatizacio
A38: 3 | B38: Articulo | C38: EstufaGas | D38: EstufaElectr | E38: VentPedestal | F38: Vent_Torre | G38: Purif_Aire | H38: Deshumidific | I38: Ionizador
A39: 3 | B39: Precio promedio historico unidades vendidas a consumidores | C39: 91.5 | D39: 113.5 | E39: 38.67 | F39: 53.33 | G39: 81.67 | H39: 117 | I39: 82
A40: 3 | B40: Variacion de precio respecto periodo anterior (%) | C40: 0.021 | D40: 0.017 | E40: 0.026 | F40: 0 | G40: 0.048 | H40: 0 | I40: 0
A41: 3 | B41: Precio que consumidores estan dispuestos a pagar | C41: 97 | D41: 121 | E41: 40 | F41: 56 | G41: 86 | H41: 120 | I41: 85
A42: 3 | B42: Precio promedio ofrecido a consumidores en periodo 7 | C42: 97 | D42: 120 | E42: 40 | F42: 55 | G42: 87 | H42: 117 | I42: 82
A43: 3 | B43: Ventas a consumidores total | C43: 82593 | D43: 81633 | E43: 121401 | F43: 84652 | G43: 109884 | H43: 65016 | I43: 9575
A44: 3 | B44: Empresas vendiendo a consumidores | C44: 21 | D44: 21 | E44: 22 | F44: 23 | G44: 29 | H44: 15 | I44: 3
A45: 3 | B45: Empresas presentes en mcdo. consumidores con linea de productos | C45: 35 | D45: 35 | E45: 35 | F45: 35 | G45: 35 | H45: 35 | I45: 35
A46: 3 | B46: Inventario final | C46: 267438 | D46: 290286 | E46: 363426 | F46: 285324 | G46: 433912 | H46: 121533 | I46: 85826
A47: 3 | B47: Cantidad producida este periodo | C47: 116749 | D47: 115436 | E47: 255734 | F47: 208288 | G47: 241266 | H47: 54177 | I47: 52467
A48: 3 | B48: Gasto promedio en publicidad y promociones | C48: 101060 | D48: 100786 | E48: 101795 | F48: 107446 | G48: 91078 | H48: 110567 | I48: 100167
A49: 3 | B49: Gasto promedio en Servicio Post-Venta | C49: 29905 | D49: 28167 | E49: 32727 | F49: 31978 | G49: 29500 | H49: 31433 | I49: 30333
A50: 3 | B50: Promedio de Puntos de Venta | C50: 4 | D50: 4 | E50: 4 | F50: 4 | G50: 3 | H50: 4 | I50: 1
A51: 3 | B51: Gasto promedio en Responsabilidad Social | C51: 31027 | D51: 32084 | E51: 36647 | F51: 35882 | G51: 28960 | H51: 37773 | I51: 11667
A52: 3 | B52: Informacion detallada de Alemania para Electrodomes hasta el periodo 7.
A53: 3 | B53: Pais | C53: Alemania | D53: Alemania | E53: Alemania | F53: Alemania | G53: Alemania | H53: Alemania | I53: Alemania
A54: 3 | B54: Lineas de Productos | C54: Electrodomes | D54: Electrodomes | E54: Electrodomes | F54: Electrodomes | G54: Electrodomes | H54: Electrodomes | I54: Electrodomes
A55: 3 | B55: Articulo | C55: Hervidor | D55: Tostador | E55: Batidora | F55: Cafetera | G55: Licuadora | H55: FreidoraAire | I55: ParrilaElect
A56: 3 | B56: Precio promedio historico unidades vendidas a consumidores | C56: 30.33 | D56: 26.33 | E56: 26.83 | F56: 35.83 | G56: 38 | H56: 65 | I56: 56
A57: 3 | B57: Variacion de precio respecto periodo anterior (%) | C57: 0.032 | D57: 0.037 | E57: 0 | F57: 0.027 | G57: 0.051 | H57: 0 | I57: 0
A58: 3 | B58: Precio que consumidores estan dispuestos a pagar | C58: 32 | D58: 29 | E58: 28 | F58: 39 | G58: 40 | H58: 65 | I58: 55
A59: 3 | B59: Precio promedio ofrecido a consumidores en periodo 7 | C59: 32 | D59: 28 | E59: 28 | F59: 38 | G59: 41 | H59: 65 | I59: 56
A60: 3 | B60: Ventas a consumidores total | C60: 141222 | D60: 108293 | E60: 121688 | F60: 131051 | G60: 105411 | H60: 65394 | I60: 2573
A61: 3 | B61: Empresas vendiendo a consumidores | C61: 25 | D61: 18 | E61: 20 | F61: 24 | G61: 20 | H61: 12 | I61: 1
A62: 3 | B62: Empresas presentes en mcdo. consumidores con linea de productos | C62: 29 | D62: 29 | E62: 29 | F62: 29 | G62: 29 | H62: 29 | I62: 29
A63: 3 | B63: Inventario final | C63: 427557 | D63: 414306 | E63: 480691 | F63: 422466 | G63: 295881 | H63: 148535 | I63: 94425
A64: 3 | B64: Cantidad producida este periodo | C64: 207207 | D64: 227421 | E64: 279222 | F64: 236963 | G64: 164636 | H64: 48645 | I64: 57318
A65: 3 | B65: Gasto promedio en publicidad y promociones | C65: 91980 | D65: 97472 | E65: 99295 | F65: 92238 | G65: 97305 | H65: 98842 | I65: 79400
A66: 3 | B66: Gasto promedio en Servicio Post-Venta | C66: 29520 | D66: 29667 | E66: 28800 | F66: 28208 | G66: 30800 | H66: 30667 | I66: 21000
A67: 3 | B67: Promedio de Puntos de Venta | C67: 2 | D67: 2 | E67: 2 | F67: 2 | G67: 2 | H67: 2 | I67: 1
A68: 3 | B68: Gasto promedio en Responsabilidad Social | C68: 25128 | D68: 27538 | E68: 25798 | F68: 25953 | G68: 26173 | H68: 26021 | I68: 0
A69: 4 | B69: Informacion detallada de Australia para Electrodomes hasta el periodo 7.
A70: 4 | B70: Pais | C70: Australia | D70: Australia | E70: Australia | F70: Australia | G70: Australia | H70: Australia | I70: Australia
A71: 4 | B71: Lineas de Productos | C71: Electrodomes | D71: Electrodomes | E71: Electrodomes | F71: Electrodomes | G71: Electrodomes | H71: Electrodomes | I71: Electrodomes
A72: 4 | B72: Articulo | C72: Hervidor | D72: Tostador | E72: Batidora | F72: Cafetera | G72: Licuadora | H72: FreidoraAire | I72: ParrilaElect
A73: 4 | B73: Precio promedio historico unidades vendidas a consumidores | C73: 34.67 | D73: 33.33 | E73: 27 | F73: 44.83 | G73: 47.5 | H73: 65 | I73: 50
A74: 4 | B74: Variacion de precio respecto periodo anterior (%) | C74: 0.029 | D74: 0.029 | E74: 0.036 | F74: 0 | G74: 0.02 | H74: 0 | I74: 0
A75: 4 | B75: Precio que consumidores estan dispuestos a pagar | C75: 37 | D75: 35 | E75: 28 | F75: 47 | G75: 50 | H75: 65 | I75: 0
A76: 4 | B76: Precio promedio ofrecido a consumidores en periodo 7 | C76: 36 | D76: 35 | E76: 29 | F76: 45 | G76: 50 | H76: 65 | I76: 0
A77: 4 | B77: Ventas a consumidores total | C77: 160562 | D77: 107969 | E77: 160219 | F77: 165104 | G77: 109402 | H77: 68100 | I77: 0
A78: 4 | B78: Empresas vendiendo a consumidores | C78: 30 | D78: 25 | E78: 26 | F78: 32 | G78: 30 | H78: 11 | I78: 0
A79: 4 | B79: Empresas presentes en mcdo. consumidores con linea de productos | C79: 39 | D79: 39 | E79: 39 | F79: 39 | G79: 39 | H79: 39 | I79: 0
A80: 4 | B80: Inventario final | C80: 455324 | D80: 398832 | E80: 339874 | F80: 421229 | G80: 314030 | H80: 168062 | I80: 102959
A81: 4 | B81: Cantidad producida este periodo | C81: 209172 | D81: 195682 | E81: 135020 | F81: 164346 | G81: 105891 | H81: 39853 | I81: 42483
A82: 4 | B82: Gasto promedio en publicidad y promociones | C82: 87020 | D82: 93584 | E82: 96492 | F82: 88584 | G82: 93290 | H82: 107173 | I82: 0
A83: 4 | B83: Gasto promedio en Servicio Post-Venta | C83: 31600 | D83: 33320 | E83: 33808 | F83: 31906 | G83: 31600 | H83: 41364 | I83: 0
A84: 4 | B84: Promedio de Puntos de Venta | C84: 3 | D84: 3 | E84: 3 | F84: 3 | G84: 3 | H84: 3 | I84: 0
A85: 4 | B85: Gasto promedio en Responsabilidad Social | C85: 27110 | D85: 27385 | E85: 27266 | F85: 26177 | G85: 27516 | H85: 25412 | I85: 0
A86: 5 | B86: Informacion detallada de Espana para Electrodomes hasta el periodo 7.
A87: 5 | B87: Pais | C87: Espana | D87: Espana | E87: Espana | F87: Espana | G87: Espana | H87: Espana | I87: Espana
A88: 5 | B88: Lineas de Productos | C88: Electrodomes | D88: Electrodomes | E88: Electrodomes | F88: Electrodomes | G88: Electrodomes | H88: Electrodomes | I88: Electrodomes
A89: 5 | B89: Articulo | C89: Hervidor | D89: Tostador | E89: Batidora | F89: Cafetera | G89: Licuadora | H89: FreidoraAire | I89: ParrilaElect
A90: 5 | B90: Precio promedio historico unidades vendidas a consumidores | C90: 27.5 | D90: 26.67 | E90: 23.83 | F90: 30.67 | G90: 31.5 | H90: 61 | I90: 53
A91: 5 | B91: Variacion de precio respecto periodo anterior (%) | C91: 0.036 | D91: 0.074 | E91: 0.04 | F91: 0 | G91: 0.061 | H91: 0 | I91: 0
A92: 5 | B92: Precio que consumidores estan dispuestos a pagar | C92: 29 | D92: 28 | E92: 25 | F92: 32 | G92: 32 | H92: 60 | I92: 55
A93: 5 | B93: Precio promedio ofrecido a consumidores en periodo 7 | C93: 29 | D93: 29 | E93: 26 | F93: 33 | G93: 35 | H93: 61 | I93: 53
A94: 5 | B94: Ventas a consumidores total | C94: 137025 | D94: 91544 | E94: 171943 | F94: 117641 | G94: 94820 | H94: 107545 | I94: 9051
A95: 5 | B95: Empresas vendiendo a consumidores | C95: 24 | D95: 19 | E95: 29 | F95: 25 | G95: 22 | H95: 20 | I95: 4
A96: 5 | B96: Empresas presentes en mcdo. consumidores con linea de productos | C96: 35 | D96: 35 | E96: 35 | F96: 35 | G96: 35 | H96: 35 | I96: 35
A97: 5 | B97: Inventario final | C97: 425066 | D97: 416838 | E97: 431641 | F97: 414919 | G97: 300930 | H97: 185713 | I97: 139597
A98: 5 | B98: Cantidad producida este periodo | C98: 229019 | D98: 249303 | E98: 240113 | F98: 245822 | G98: 174855 | H98: 91478 | I98: 102594
A99: 5 | B99: Gasto promedio en publicidad y promociones | C99: 101375 | D99: 102671 | E99: 92250 | F99: 95310 | G99: 107045 | H99: 87725 | I99: 70875
A100: 5 | B100: Gasto promedio en Servicio Post-Venta | C100: 24750 | D100: 26053 | E100: 23069 | F100: 24000 | G100: 25636 | H100: 22500 | I100: 21000
...
